Workbook

Sheet BALANCE DE SITUACIÓN
A1: BALANCE DE SITUACIÓN NORMAL | H1: Hecho por:
A2: ACTIVO | C2: EJERCICIO 2023 | D2: EJERCICIO 2022 | E2: PORCENTAJES 2023 | F2: PORCENTAJES 2022 | H2: Francisco Javier Checa Casas
A3: A) ACTIVO NO CORRIENTE | C3: 517370 | D3: 455451 | E3: 1 | F3: 1 | H3: Tomasso Sgroi
A4: I. Inmovilizado Intangible | C4: 3257 | D4: 4472 | E4: =C4/$C$3 -> 0.0062953012 | F4: =D4/$D$3 -> 0.0098188389
A5: 1. Desarrollo
A6: 2. Concesiones
A7: 3. Patentes, licencias, marcas y similares
A8: 4. Fondo de comercio
A9: 5. Aplicaciones informáticas | C9: 1065 | D9: 992 | E9: =C9/$C$3 -> 0.0020584881 | F9: =D9/$D$3 -> 0.0021780609
A10: 6. Investigación | C10: 2192 | D10: 3467 | E10: =C10/$C$3 -> 0.0042368131 | F10: =D10/$D$3 -> 0.0076122349
A11: 7. Propiedad intelectual
A12: 8. Otro inmovilizado intangible | C12: 0 | D12: 13 | F12: =D12/$D$3 -> 2.8543136e-05
A13: II. Inmovilizado material | C13: 385465 | D13: 381953 | E13: =C13/$C$3 -> 0.74504706 | F13: =D13/$D$3 -> 0.83862589
A14: 1. Terrenos y construcciones | C14: 93058 | D14: 91631 | E14: =C14/$C$3 -> 0.17986741 | F14: =D14/$D$3 -> 0.20118739
A15: 2. Instalaciones técnicas y otro inmovilizado material | C15: 267325 | D15: 269006 | E15: =C15/$C$3 -> 0.51669985 | F15: =D15/$D$3 -> 0.59063653
A16: 3. Inmovilizado en curso y anticipos | C16: 25082 | D16: 21316 | E16: =C16/$C$3 -> 0.048479811 | F16: =D16/$D$3 -> 0.046801961
A17: III. Inversiones inmobiliarias | C17: 7943 | D17: 8054 | E17: =C17/$C$3 -> 0.015352649 | F17: =D17/$D$3 -> 0.017683571
A18: 1. Terrenos | C18: 4212 | D18: 4212 | E18: =C18/$C$3 -> 0.0081411756 | F18: =D18/$D$3 -> 0.0092479762
A19: 2. Construcciones | C19: 3731 | D19: 3842 | E19: =C19/$C$3 -> 0.0072114734 | F19: =D19/$D$3 -> 0.0084355946
A20: IV. Inversiones en empresas de grupo y asociadas a largo plazo | C20: 2705 | D20: 2705 | E20: =C20/$C$3 -> 0.0052283665 | F20: =D20/$D$3 -> 0.005939168
A21: 1. Instrumentos de patrimonio | C21: 2705 | D21: 2705 | E21: =C21/$C$3 -> 0.0052283665 | F21: =D21/$D$3 -> 0.005939168
A22: 2. Créditos a empresas
A23: 3. Valores representativos de deuda
A24: 4. Derivados
A25: 5. Otros activos financieros
A26: 6. Otras inversiones
A27: V. Inversiones financieras a largo plazo | C27: 389 | D27: 1070 | E27: =C27/$C$3 -> 0.0007518797 | F27: =D27/$D$3 -> 0.0023493197
A28: 1. Instrumentos de patrimonio | C28: 275 | D28: 275 | E28: =C28/$C$3 -> 0.00053153449 | F28: =D28/$D$3 -> 0.00060379712
A29: 2. Créditos a terceros
A30: 3. Valores representativos de deuda
A31: 4. Derivados
A32: 5. Otros activos financieros | C32: 114 | D32: 795 | E32: =C32/$C$3 -> 0.00022034521 | F32: =D32/$D$3 -> 0.0017455226
A33: 6. Otras inversiones
A34: VI. Activos por Impuesto diferido | C34: 117611 | D34: 57197 | E34: =C34/$C$3 -> 0.22732474 | F34: =D34/$D$3 -> 0.12558321
A35: VII. Deudores comerciales no corrientes
A36: B) ACTIVO CORRIENTE | C36: 625068 | D36: 738462 | E36: 1 | F36: 1
A37: I. Activos no corrientes mantenidos para la venta
A38: II. Existencias | C38: 421245 | D38: 477896 | E38: =C38/$C$36 -> 0.67391868 | F38: =D38/$D$36 -> 0.64715043
A39: 1. Comerciales
A40: 2. Materias primas y otros aprovisionamientos | C40: 160765 | D40: 184275 | E40: =C40/$C$36 -> 0.25719602 | F40: =D40/$D$36 -> 0.24953891
A41: a) Materias primas y otros aprovisionamientos a largo plazo
A42: b) Materias primas y otros aprovisionamientos a corto plazo | C42: 160765 | D42: 184275 | E42: =C42/$C$36 -> 0.25719602 | F42: =D42/$D$36 -> 0.24953891
A43: 3. Productos en curso | C43: 124468 | D43: 132594 | E43: =C43/$C$36 -> 0.19912713 | F43: =D43/$D$36 -> 0.17955426
A44: a) De ciclo largo de producción
A45: b) De ciclo corto de producción | C45: 124468 | D45: 132594 | E45: =C45/$C$36 -> 0.19912713 | F45: =D45/$D$36 -> 0.17955426
A46: 4. Productos terminados | C46: 110743 | D46: 118668 | E46: =C46/$C$36 -> 0.17716952 | F46: =D46/$D$36 -> 0.16069615
A47: a) De ciclo largo de producción
A48: b) De ciclo corto de producción | C48: 110743 | D48: 118668 | E48: =C48/$C$36 -> 0.17716952 | F48: =D48/$D$36 -> 0.16069615
A49: 5. Subproductos, residuos y materias recuperados | C49: 25269 | D49: 42359 | E49: =C49/$C$36 -> 0.040426002 | F49: =D49/$D$36 -> 0.05736111
A50: 6. Anticipos a proveedores
A51: III. Deudores comercuales y otras cuentas a cobrar | C51: 197821 | D51: 257849 | E51: =C51/$C$36 -> 0.31647917 | F51: =D51/$D$36 -> 0.3491703
A52: 1. Clientes por ventas y prestaciones de servicios | C52: 78642 | D52: 48170 | E52: =C52/$C$36 -> 0.12581351 | F52: =D52/$D$36 -> 0.065230168
A53: a) Clientes por ventas y prestaciones de servicios a largo plazo
A54: b) Clientes por ventas y prestaciones de servicios a corto plazo | C54: 78642 | D54: 48170 | E54: =C54/$C$36 -> 0.12581351 | F54: =D54/$D$36 -> 0.065230168
A55: 2. Clientes empresas del grupo y asociadas | C55: 102105 | D55: 203823 | E55: =C55/$C$36 -> 0.16335023 | F55: =D55/$D$36 -> 0.27601014
A56: 3. Deudores varios | C56: 12511 | D56: 544 | E56: =C56/$C$36 -> 0.020015422 | F56: =D56/$D$36 -> 0.00073666621
A57: 4. Personal | C57: 381 | D57: 859 | E57: =C57/$C$36 -> 0.00060953368 | F57: =D57/$D$36 -> 0.0011632284
A58: 5. Activos por impuesto corriente | C58: 10 | D58: 10 | E58: =C58/$C$36 -> 1.5998259e-05 | F58: =D58/$D$36 -> 1.3541658e-05
A59: 6. Otros créditos con las Administraciones Públicas | C59: 4172 | D59: 4443 | E59: =C59/$C$36 -> 0.0066744738 | F59: =D59/$D$36 -> 0.0060165587
A60: 7. Accionistas (socios) por desembolsos exigidos
A61: IV. Inversiones en empresas del grupo y asociadas a corto plazo | C61: 770 | D61: 0 | E61: =C61/$C$36 -> 0.001231866
A62: 1. Instrumentos de patrimonio
A63: 2. Créditos a empresas | C63: 770 | D63: 0 | E63: =C63/$C$36 -> 0.001231866
A64: 3. Valores representativos de deuda
A65: 4. Derivados
A66: 5. Otros activos financieros
A67: 6. Otras inversiones
A68: V. Inversiones financieras a corto plazo | C68: 80 | D68: 308 | E68: =C68/$C$36 -> 0.00012798608 | F68: =D68/$D$36 -> 0.00041708307
A69: 1. Instrumentos de patrimonio
A70: 2. Créditos a empresas
A71: 3. Valores representativos de deuda
A72: 4. Derivados | C72: 80 | D72: 304 | E72: =C72/$C$36 -> 0.00012798608 | F72: =D72/$D$36 -> 0.00041166641
A73: 5. Otros activos financieros | C73: 0 | D73: 4 | F73: =D73/$D$36 -> 5.4166633e-06
A74: 6. Otras inversiones
A75: VI. Periodificaciones a corto plazo | C75: 1703 | D75: 1134 | E75: =C75/$C$36 -> 0.0027245036 | F75: =D75/$D$36 -> 0.001535624
A76: VII. Efectivo y otros activos líquidos equivalentes | C76: 3449 | D76: 1275 | E76: =C76/$C$36 -> 0.0055177997 | F76: =D76/$D$36 -> 0.0017265614
A77: 1. Tesorería | C77: 3449 | D77: 1275 | E77: =C77/$C$36 -> 0.0055177997 | F77: =D77/$D$36 -> 0.0017265614
A78: 2. Otros activos líquidos equivalentes
A79: TOTAL ACTIVO (A+B) | C79: 1142438 | D79: 1193913
A83: PATRIMONIO NETO Y PASIVO
A84: A) PATRIMONIO NETO | C84: 53265 | D84: 242867 | E84: 1 | F84: 1
A85: A-1) Fondos propios | C85: 27434 | D85: 223204 | E85: =C85/$C$84 -> 0.5150474 | F85: =D85/$D$84 -> 0.91903799
A86: I. Capital | C86: 62000 | D86: 62000 | E86: =C86/$C$84 -> 1.1639914 | F86: =D86/$D$84 -> 0.25528376
A87: 1. Capital escriturado | C87: 62000 | D87: 62000 | E87: =C87/$C$84 -> 1.1639914 | F87: =D87/$D$84 -> 0.25528376
A88: 2. (Capital no exigido)
A89: II. Prima de emisión | C89: 279381 | D89: 279381 | E89: =C89/$C$84 -> 5.2451141 | F89: =D89/$D$84 -> 1.1503457
A90: III. Reservas | C90: 34242 | D90: 34242 | E90: =C90/$C$84 -> 0.64286117 | F90: =D90/$D$84 -> 0.14099075
A91: 1. Legal y estatutarias | C91: 12400 | D91: 12400 | E91: =C91/$C$84 -> 0.23279827 | F91: =D91/$D$84 -> 0.051056751
A92: 2. Otras reservas | C92: 21842 | D92: 21842 | E92: =C92/$C$84 -> 0.41006289 | F92: =D92/$D$84 -> 0.089933997
A93: 3. Reserva de revalorización
A94: 4. Reserva de capitalización
A95: IV. (Acciones y participaciones en patrimonio propias)
A96: V. Resultados de ejercicios anteriores | C96: -152475 | D96: -91747 | E96: =C96/$C$84 -> -2.8625739 | F96: =D96/$D$84 -> -0.37776643
A97: 1. Remanente
A98: 2. (Resultados negativos de ejercicios anteriores)
A99: VI. Otras aportaciones de socios | C99: 98 | D99: 56 | E99: =C99/$C$84 -> 0.0018398573 | F99: =D99/$D$84 -> 0.00023057888
A100: VII. Resultado del ejercicio | C100: -195812 | D100: -60728 | E100: =C100/$C$84 -> -3.6761851 | F100: =D100/$D$84 -> -0.25004632
A101: VIII. (Dividendo a cuenta)
A102: IX. Otros intrumentos de patrimonio neto
A103: A-2) Ajustes por cambios de valor
...

Sheet CUENTA DE PÉRDIDAS Y GANANCIAS
A1: CUENTA DE PÉRDIDAS Y GANANCIAS
A2: (DEBE)/HABER | C2: EJERCICIO 2023 | D2: EJERCICIO 2022
A3: A) OPERACIONES CONTINUADAS
A4: 1. Importe neto de la cifra de negocios | C4: 1313068 | D4: 1912676
A5: a) Ventas | C5: 1303704 | D5: 1910141
A6: b) Prestaciones de servicios | C6: 9364 | D6: 2535
A7: c) Ingresos de carácter financiero de las sociedades holding
A8: 2. Variación de existencias de productos terminados y en curso de fabricación | C8: -33140 | D8: 11384
A9: 3. Trabajos realizados por la empresa para su activo | C9: 6129 | D9: 25315
A10: l | C10: -1137455 | D10: -1450909
A11: a) Consumo de mercaderías | C11: -9533 | D11: -51999
A12: b) Consumo de materias primas y otras materias consumibles | C12: -1127688 | D12: -1398368
A13: c) Ingresos de carácter financiero de las sociedades holding | C13: -3 | D13: -357
A14: d) Deterioro de mercaderías, materias primas y otros aprovisionamientos | C14: -231 | D14: -195
A15: 5. Otros ingresos de explotación | C15: 31624 | D15: 16310
A16: a) Ingresos accesorios y otros de gestión corriente | C16: 5445 | D16: 2656
A17: b) Subvenciones de explotación incorporadas al resultado del ejercicio | C17: 26179 | D17: 13654
A18: 6. Gastos de personal | C18: -124720 | D18: -129817
A19: a) Sueldos, salarios y asimilados | C19: -90043 | D19: -93956
A20: b) Cargas sociales | C20: -34677 | D20: -35861
A21: c) Provisiones
A22: 7. Otros gastos de explotación | C22: -245240 | D22: -425170
A23: a) Servicios exteriores | C23: -234655 | D23: -415862
A24: b) Tributos | C24: -3267 | D24: -3116
A25: c) Pérdidas, deterioro y variación de provisiones por operaciones comerciales | C25: -1 | D25: 0
A26: d) Otros gastos de gestión corriente | C26: -7317 | D26: -6192
A27: e) Gastos por emisión de gases de efecto invernadero
A28: 8. Amortización del inmovilizado | C28: -36003 | D28: -30024
A29: 9. Imputación de subvenciones de inmovilizado no financiero y otras | C29: 1172 | D29: 217
A30: 10. Excesos de provisiones
A31: 11. Deterioro y resultado por enajenaciones del inmovilizado | C31: -411 | D31: -241
A32: a) Deterioro y pérdidas
A33: b) Resultados por enajenaciones y otras | C33: -411 | D33: -241
A34: c) Deterioro y resultados por enajenaciones del inmovilizado de las sociedades holding
A35: 12. Diferencia negativa de combinaciones de negocio
A36: 13. Otros resultados
A37: A.1) RESULTADO DE EXPLOTACIÓN (1+2+3+4+5+6+7+8+9+10+11+12+13) | C37: -224976 | D37: -70259
A38: 14. Ingresos financieros | C38: 350 | D38: 1903
A39: a) De participaciones en instrumentos de patrimonio
A40: a1) En empresas del grupo y asociadas
A41: a2) En terceros
A42: b) De valores negociables y otros instrumentos financieros | C42: 350 | D42: 1903
A43: b1) De empresas del grupo y asociadas | C43: 247 | D43: 1890
A44: b2) De terceros | C44: 103 | D44: 13
A45: c) Imputación de subvenciones, donaciones y legados de carácter
A46: 15. Gastos financieros | C46: -39155 | D46: -16235
A47: a) Por deudas con empresas del grupo y asociadas | C47: -22513 | D47: -8959
A48: b) Por deudas con terceros | C48: -16642 | D48: -7276
A49: c) Por actualización de provisiones
A50: 16. Variación de valor razonable en instrumentos financieros | C50: 1643 | D50: -3525
A51: a) Valor razonable con cambios en pérdidas y ganancias | C51: 1643 | D51: -3525
A52: b) Transferencia de ajustes de valor razonable con cambios en el patrimonio neto
A53: 17. Diferencias de cambio | C53: -332 | D53: 4900
A54: 18. Deterioro y resultado por enajenaciones de instrumentos financieros
A55: a) Deterioros y pérdidas
A56: b) Resultados por enajenaciones y otras
A57: 19. Otros ingresos y gastos de carácter financiero
A58: a) Incorporación al activo de gastos financieros
A59: b) Ingresos financieros derivados de convenios de acreedores
A60: c) Resto de ingresos y gastos
A61: A.2) RESULTADO FINANCIERO (14+15+16+17+18+19) | C61: -37494 | D61: -12957
A62: A.3) RESULTADO ANTES DE IMPUESTOS (A.1+A.2) | C62: -262470 | D62: -83216
A63: 20. Impuesto sobre beneficios | C63: 66658 | D63: 22488
A64: A.4) RESULTADO DEL EJERCICIO PROCEDENTE DE OPERACIONES CONTINUADAS (A.3+20) | C64: -195812 | D64: -60728
A65: B) OPERACIONES INTERRUMPIDAS
A66: 21. Resultado del ejercicio procedente de operaciones interrumpidas neto de impuestos
A67: A.5) RESULTADO DEL EJERCICIO (A.4+21) | C67: -195812 | D67: -60728

Sheet RATIOS
A1: ACERINOX | B1: EJERCICIO 2022 | C1: EJERCICIO 2023 | D1: PROMEDIO EMPRESAS EN EL MISMO SECTOR (2022) | E1: PROMEDIO EMPRESAS EN EL MISMO SECTOR (2023) | G1: FONDO DE MANIOBRA | H1: (Activo Corriente - Pasivo Corriente)
A2: RATIOS DE LIQUIDEZ | G2: 2023 | H2: ='BALANCE DE SITUACIÓN'!C36-'BALANCE DE SITUACIÓN'!C127 -> -406341
A3: RATIO DE LIQUIDEZ | B3: ='BALANCE DE SITUACIÓN'!D36/'BALANCE DE SITUACIÓN'!D127 -> 0.82671369 | C3: ='BALANCE DE SITUACIÓN'!C36/'BALANCE DE SITUACIÓN'!C127 -> 0.60603311 | D3: =AVERAGE(SUBSTITUTE('DATOS SECTOR'!D15,".",",")*1,SUBSTITUTE('DATOS SECTOR'!D16,".",",")*1,SUBSTITUTE('DATOS SECTOR'!D17,".",",")*1,SUBSTITUTE('DATOS SECTOR'!D19,".",",")*1) -> 1.14 | E3: =AVERAGE(SUBSTITUTE('DATOS SECTOR'!D6,".",",")*1,SUBSTITUTE('DATOS SECTOR'!D7,".",",")*1,SUBSTITUTE('DATOS SECTOR'!D8,".",",")*1,SUBSTITUTE('DATOS SECTOR'!D10,".",",")*1) -> 1.1025 | G3: 2022 | H3: ='BALANCE DE SITUACIÓN'!D36-'BALANCE DE SITUACIÓN'!D127 -> -154788
A4: RATIO DE TESORERÍA | B4: =('BALANCE DE SITUACIÓN'!D36-'BALANCE DE SITUACIÓN'!D38)/'BALANCE DE SITUACIÓN'!D127 -> 0.29170557 | C4: =('BALANCE DE SITUACIÓN'!C36-'BALANCE DE SITUACIÓN'!C38)/'BALANCE DE SITUACIÓN'!C127 -> 0.19761608
A5: RATIO DE DISPONIBILIDAD | B5: ='BALANCE DE SITUACIÓN'!D76/'BALANCE DE SITUACIÓN'!D127 -> 0.001427372 | C5: ='BALANCE DE SITUACIÓN'!C76/'BALANCE DE SITUACIÓN'!C127 -> 0.0033439693 | D5: =AVERAGE('DATOS SECTOR'!R15/'DATOS SECTOR'!T15,'DATOS SECTOR'!R16/'DATOS SECTOR'!T16,'DATOS SECTOR'!R17/'DATOS SECTOR'!T17,'DATOS SECTOR'!R19/'DATOS SECTOR'!T19) -> 0.20171872 | E5: =AVERAGE('DATOS SECTOR'!R6/'DATOS SECTOR'!T6,'DATOS SECTOR'!R7/'DATOS SECTOR'!T7,'DATOS SECTOR'!R8/'DATOS SECTOR'!T8,'DATOS SECTOR'!R10/'DATOS SECTOR'!T10) -> 0.15299031
A6: RATIO DE F.M SOBRE ACTIVO | B6: =H3/'BALANCE DE SITUACIÓN'!D79 -> -0.12964764 | C6: =H2/'BALANCE DE SITUACIÓN'!C79 -> -0.35567882 | D6: =AVERAGE(SUBSTITUTE('DATOS SECTOR'!V15,".",",")*1,SUBSTITUTE('DATOS SECTOR'!V16,".",",")*1,SUBSTITUTE('DATOS SECTOR'!V17,".",",")*1,SUBSTITUTE('DATOS SECTOR'!V19,".",",")*1) -> 0.0575 | E6: =AVERAGE(SUBSTITUTE('DATOS SECTOR'!V6,".",",")*1,SUBSTITUTE('DATOS SECTOR'!V7,".",",")*1,SUBSTITUTE('DATOS SECTOR'!V8,".",",")*1,SUBSTITUTE('DATOS SECTOR'!V10,".",",")*1) -> 0.0375
A7: RATIO DE F.M SOBRE PASIVO CORRENTE | B7: =H3/'BALANCE DE SITUACIÓN'!D127 -> -0.17328631 | C7: =H2/'BALANCE DE SITUACIÓN'!C127 -> -0.39396689 | D7: =AVERAGE((SUBSTITUTE('DATOS SECTOR'!D15,".",",")*1-1),(SUBSTITUTE('DATOS SECTOR'!D16,".",",")*1-1),(SUBSTITUTE('DATOS SECTOR'!D17,".",",")*1-1),(SUBSTITUTE('DATOS SECTOR'!D19,".",",")*1-1)) -> 0.14 | E7: =AVERAGE((SUBSTITUTE('DATOS SECTOR'!D6,".",",")*1-1),(SUBSTITUTE('DATOS SECTOR'!D7,".",",")*1-1),(SUBSTITUTE('DATOS SECTOR'!D8,".",",")*1-1),(SUBSTITUTE('DATOS SECTOR'!D10,".",",")*1-1)) -> 0.1025
A8: RATIOS DE ENDEUDAMIENTO
A9: RATIO DE ENDEUDAMIENTO | B9: =('BALANCE DE SITUACIÓN'!D127+'BALANCE DE SITUACIÓN'!D110)/('BALANCE DE SITUACIÓN'!D84+('BALANCE DE SITUACIÓN'!D127+'BALANCE DE SITUACIÓN'!D110)) -> 0.79657898 | C9: =('BALANCE DE SITUACIÓN'!C110+'BALANCE DE SITUACIÓN'!C127)/('BALANCE DE SITUACIÓN'!C84+('BALANCE DE SITUACIÓN'!C110+'BALANCE DE SITUACIÓN'!C127)) -> 0.95337603 | D9: =AVERAGE(SUBSTITUTE('DATOS SECTOR'!F15,".",",")*1,SUBSTITUTE('DATOS SECTOR'!F16,".",",")*1,SUBSTITUTE('DATOS SECTOR'!F17,".",",")*1,SUBSTITUTE('DATOS SECTOR'!F19,".",",")*1)/100 -> 0.638625 | E9: =AVERAGE(SUBSTITUTE('DATOS SECTOR'!F6,".",",")*1,SUBSTITUTE('DATOS SECTOR'!F7,".",",")*1,SUBSTITUTE('DATOS SECTOR'!F8,".",",")*1,SUBSTITUTE('DATOS SECTOR'!F10,".",",")*1)/100 -> 0.567125
A10: RATIO DE AUTONOMÍA | B10: ='BALANCE DE SITUACIÓN'!D84/('BALANCE DE SITUACIÓN'!D127+'BALANCE DE SITUACIÓN'!D110) -> 0.2553683 | C10: ='BALANCE DE SITUACIÓN'!C84/('BALANCE DE SITUACIÓN'!C110+'BALANCE DE SITUACIÓN'!C127) -> 0.048904077 | D10: =AVERAGE('DATOS SECTOR'!N15/('DATOS SECTOR'!J15-'DATOS SECTOR'!N15),'DATOS SECTOR'!N16/('DATOS SECTOR'!J16-'DATOS SECTOR'!N16),'DATOS SECTOR'!N17/('DATOS SECTOR'!J17-'DATOS SECTOR'!N17),'DATOS SECTOR'!N19/('DATOS SECTOR'!J19-'DATOS SECTOR'!N19)) -> 0.58122674 | E10: =AVERAGE('DATOS SECTOR'!N6/('DATOS SECTOR'!J6-'DATOS SECTOR'!N6),'DATOS SECTOR'!N7/('DATOS SECTOR'!J7-'DATOS SECTOR'!N7),'DATOS SECTOR'!N8/('DATOS SECTOR'!J8-'DATOS SECTOR'!N8),'DATOS SECTOR'!N10/('DATOS SECTOR'!J10-'DATOS SECTOR'!N10)) -> 0.79400207
A11: RATIO DE SOLVENCIA O GARANTÍA | B11: ='BALANCE DE SITUACIÓN'!D79/('BALANCE DE SITUACIÓN'!D110+'BALANCE DE SITUACIÓN'!D127) -> 1.2553683 | C11: ='BALANCE DE SITUACIÓN'!C79/('BALANCE DE SITUACIÓN'!C110+'BALANCE DE SITUACIÓN'!C127) -> 1.0489041 | D11: =AVERAGE(SUBSTITUTE('DATOS SECTOR'!Z15,".",",")*1,SUBSTITUTE('DATOS SECTOR'!Z16,".",",")*1,SUBSTITUTE('DATOS SECTOR'!Z17,".",",")*1,SUBSTITUTE('DATOS SECTOR'!Z19,".",",")*1) -> 1.14 | E11: =AVERAGE(SUBSTITUTE('DATOS SECTOR'!Z6,".",",")*1,SUBSTITUTE('DATOS SECTOR'!Z7,".",",")*1,SUBSTITUTE('DATOS SECTOR'!Z8,".",",")*1,SUBSTITUTE('DATOS SECTOR'!Z10,".",",")*1) -> 1.1025
A12: RATIO DE CALIDAD DE LA DEUDA | B12: ='BALANCE DE SITUACIÓN'!D127/('BALANCE DE SITUACIÓN'!D110+'BALANCE DE SITUACIÓN'!D127) -> 0.93922902 | C12: ='BALANCE DE SITUACIÓN'!C127/('BALANCE DE SITUACIÓN'!C110+'BALANCE DE SITUACIÓN'!C127) -> 0.94696527 | D12: =AVERAGE('DATOS SECTOR'!T15/('DATOS SECTOR'!J15-'DATOS SECTOR'!N15),'DATOS SECTOR'!T16/('DATOS SECTOR'!J16-'DATOS SECTOR'!N16),'DATOS SECTOR'!T17/('DATOS SECTOR'!J17-'DATOS SECTOR'!N17),'DATOS SECTOR'!T19/('DATOS SECTOR'!J19-'DATOS SECTOR'!N19)) -> 0.73211347 | E12: =AVERAGE('DATOS SECTOR'!T6/('DATOS SECTOR'!J6-'DATOS SECTOR'!N6),'DATOS SECTOR'!T7/('DATOS SECTOR'!J7-'DATOS SECTOR'!N7),'DATOS SECTOR'!T8/('DATOS SECTOR'!J8-'DATOS SECTOR'!N8),'DATOS SECTOR'!T10/('DATOS SECTOR'!J10-'DATOS SECTOR'!N10)) -> 0.77761284
A13: RATIO DE GASTOS FINANCIEROS SOBRE VENTAS | B13: =(-1)*('CUENTA DE PÉRDIDAS Y GANANCIAS'!D46/'CUENTA DE PÉRDIDAS Y GANANCIAS'!D5) -> 0.0084993726 | C13: =(-1)*('CUENTA DE PÉRDIDAS Y GANANCIAS'!C46/'CUENTA DE PÉRDIDAS Y GANANCIAS'!C5) -> 0.030033658 | D13: =AVERAGE('DATOS SECTOR'!AD15/IF(ISTEXT('DATOS SECTOR'!AF15),SUBSTITUTE('DATOS SECTOR'!AF15,",","")*1,'DATOS SECTOR'!AF15),'DATOS SECTOR'!AD16/IF(ISTEXT('DATOS SECTOR'!AF16),SUBSTITUTE('DATOS SECTOR'!AF16,",","")*1,'DATOS SECTOR'!AF16),'DATOS SECTOR'!AD17/'DATOS SECTOR'!AF17,'DATOS SECTOR'!AD19/IF(ISTEXT('DATOS SECTOR'!AF19),SUBSTITUTE('DATOS SECTOR'!AF19,",","")*1,'DATOS SECTOR'!AF19)) -> 0.00903439 | E13: =AVERAGE('DATOS SECTOR'!AD6/'DATOS SECTOR'!AF6,'DATOS SECTOR'!AD7/'DATOS SECTOR'!AF7,'DATOS SECTOR'!AD8/'DATOS SECTOR'!AF8,'DATOS SECTOR'!AD10/IF(ISTEXT('DATOS SECTOR'!AF10),SUBSTITUTE('DATOS SECTOR'!AF10,",","")*1,'DATOS SECTOR'!AF10)) -> 0.018706742
A14: RATIO DE COSTE DE LA DEUDA | B14: =ABS('CUENTA DE PÉRDIDAS Y GANANCIAS'!D46)/('BALANCE DE SITUACIÓN'!D116+'BALANCE DE SITUACIÓN'!D122+'BALANCE DE SITUACIÓN'!D132+'BALANCE DE SITUACIÓN'!D138) -> 0.023080258 | C14: =ABS('CUENTA DE PÉRDIDAS Y GANANCIAS'!C46)/('BALANCE DE SITUACIÓN'!C116+'BALANCE DE SITUACIÓN'!C122+'BALANCE DE SITUACIÓN'!C132+'BALANCE DE SITUACIÓN'!C138) -> 0.049912425
A15: COBERTURA DE GASTOS FINANCIEROS | B15: NO CUBRE (BAII negativo) | C15: NO CUBRE (BAII negativo)
A16: RATIOS DE ROTACIÓN DE ACTIVOS
A17: RATIO DE ROTACIÓN DEL ACTIVO | B17: ='CUENTA DE PÉRDIDAS Y GANANCIAS'!D4/'BALANCE DE SITUACIÓN'!D79 -> 1.6020229 | C17: ='CUENTA DE PÉRDIDAS Y GANANCIAS'!C4/'BALANCE DE SITUACIÓN'!C79 -> 1.149356 | D17: =AVERAGE(SUBSTITUTE('DATOS SECTOR'!AH15,".",",")*1,SUBSTITUTE('DATOS SECTOR'!AH16,".",",")*1,SUBSTITUTE('DATOS SECTOR'!AH17,".",",")*1,SUBSTITUTE('DATOS SECTOR'!AH19,".",",")*1) -> 1.7725 | E17: =AVERAGE(SUBSTITUTE('DATOS SECTOR'!AH6,".",",")*1,SUBSTITUTE('DATOS SECTOR'!AH7,".",",")*1,SUBSTITUTE('DATOS SECTOR'!AH8,".",",")*1,SUBSTITUTE('DATOS SECTOR'!AH10,".",",")*1) -> 1.42
A18: RATIO DE ROTACIÓN DEL ACTIVO NO CORRIENTE | B18: ='CUENTA DE PÉRDIDAS Y GANANCIAS'!D5/'BALANCE DE SITUACIÓN'!D3 -> 4.193955 | C18: ='CUENTA DE PÉRDIDAS Y GANANCIAS'!C5/'BALANCE DE SITUACIÓN'!C3 -> 2.5198678
A19: RATIO DE ROTACIÓN DEL ACTIVO CORRIENTE | B19: ='CUENTA DE PÉRDIDAS Y GANANCIAS'!D5/'BALANCE DE SITUACIÓN'!D36 -> 2.5866477 | C19: ='CUENTA DE PÉRDIDAS Y GANANCIAS'!C5/'BALANCE DE SITUACIÓN'!C36 -> 2.0856995
A20: RATIO DE ROTACIÓN DE EXISTENCIAS | B20: =(-'CUENTA DE PÉRDIDAS Y GANANCIAS'!D10-'CUENTA DE PÉRDIDAS Y GANANCIAS'!D8)/'BALANCE DE SITUACIÓN'!D38 -> 3.012214 | C20: =(-'CUENTA DE PÉRDIDAS Y GANANCIAS'!C10-'CUENTA DE PÉRDIDAS Y GANANCIAS'!C8)/'BALANCE DE SITUACIÓN'!C38 -> 2.7788935 | D20: =AVERAGE(SUBSTITUTE('DATOS SECTOR'!AJ15,".",",")*1,SUBSTITUTE('DATOS SECTOR'!AJ16,".",",")*1,SUBSTITUTE('DATOS SECTOR'!AJ17,".",",")*1,SUBSTITUTE('DATOS SECTOR'!AJ19,".",",")*1) -> 10.2525 | E20: =AVERAGE(SUBSTITUTE('DATOS SECTOR'!AJ6,".",",")*1,SUBSTITUTE('DATOS SECTOR'!AJ7,".",",")*1,SUBSTITUTE('DATOS SECTOR'!AJ8,".",",")*1,SUBSTITUTE('DATOS SECTOR'!AJ10,".",",")*1) -> 8.7975
A21: RATIO DE ROTACIÓN DE CLIENTES | B21: ='CUENTA DE PÉRDIDAS Y GANANCIAS'!D5/('BALANCE DE SITUACIÓN'!D54+'BALANCE DE SITUACIÓN'!D55-'BALANCE DE SITUACIÓN'!D148) -> 7.5959605 | C21: ='CUENTA DE PÉRDIDAS Y GANANCIAS'!C5/('BALANCE DE SITUACIÓN'!C54+'BALANCE DE SITUACIÓN'!C55-'BALANCE DE SITUACIÓN'!C148) -> 7.5435356
A22: RATIOS DE GESTIÓN DE COBRO Y DE PAGO
A23: PLAZO DE COBRO (días) | B23: =(('BALANCE DE SITUACIÓN'!D54+'BALANCE DE SITUACIÓN'!D55-'BALANCE DE SITUACIÓN'!D148)/'CUENTA DE PÉRDIDAS Y GANANCIAS'!D4)*365 -> 47.988169 | C23: =(('BALANCE DE SITUACIÓN'!C54+'BALANCE DE SITUACIÓN'!C55-'BALANCE DE SITUACIÓN'!C148)/'CUENTA DE PÉRDIDAS Y GANANCIAS'!C4)*365 -> 48.040741
A24: PLAZO DE PAGO (días) | B24: =ABS(('BALANCE DE SITUACIÓN'!D139/'CUENTA DE PÉRDIDAS Y GANANCIAS'!D10)*365) -> 55.929004 | C24: =ABS(('BALANCE DE SITUACIÓN'!C139/'CUENTA DE PÉRDIDAS Y GANANCIAS'!C10)*365) -> 89.015069

Sheet DATOS SECTOR
A1: Nombre | B1: Código consolidación | C1: Año | D1: Liquidez general % | F1: Endeudamiento (%) % | H1: Ingresos de explotación mil EUR | J1: Total Activo mil EUR | L1: Resultado del Ejercicio mil EUR | N1: Fondos propios mil EUR | P1: Tesorería (Mil) mil | R1: Efectivo y otros activos líquidos equivalentes mil EUR | T1: Pasivo corriente mil EUR | V1: Ratio de Fondo de Maniobra % | X1: Autonomia Financeira % EUR | Z1: Ratio de solvencia % | AB1: Total pasivo mil EUR | AD1: Gastos financieros mil EUR | AF1: Importe neto Cifra de Ventas mil EUR | AH1: Rotación de activos % | AJ1: Rotación de las existencias %
A2: 2023 | E2: Rango | G2: Rango | I2: Rango | K2: Rango | M2: Rango | O2: Rango | Q2: Rango | S2: Rango | U2: Rango | W2: Rango | Y2: Rango | AA2: Rango | AC2: Rango | AE2: Rango | AG2: Rango | AI2: Rango | AK2: Rango
A3: Mediana | D3: 1.09 | F3: 57.94 | H3: 949.529 | J3: 799.162 | L3: 47.729 | N3: 199.667 | P3: 0 | R3: 15.759 | T3: 302.667 | V3: 0.04 | X3: n.d. | Z3: 1.09 | AB3: n.d. | AD3: 28.019 | AF3: 933.89 | AH3: 1.17 | AJ3: 8.16
A4: Desviación típica | D4: 0.35 | F4: 16.77 | H4: 265.229 | J4: 266.455 | L4: 99.359 | N4: 118.149 | P4: 0 | R4: 29.745 | T4: 309.107 | V4: 0.20 | X4: n.d. | Z4: 0.35 | AB4: n.d. | AD4: 12.431 | AF4: 260.801 | AH4: 0.46 | AJ4: 3.85
A5: Media | D5: 1.00 | F5: 64.44 | H5: 971.657 | J5: 759.356 | L5: -3.936 | N5: 234.832 | P5: 0 | R5: 31.409 | T5: 436.215 | V5: -0.04 | X5: n.d. | Z5: 1.00 | AB5: n.d. | AD5: 23.303 | AF5: 957.731 | AH5: 1.37 | AJ5: 7.68
A6: SIDENOR ACEROS ESPECIALES SLU | B6: U2 | C6: 2023 | D6: 1.40 | E6: 1 | F6: 56.19 | G6: 4 | H6: 949.529 | I6: 3 | J6: 799.162 | K6: 3 | L6: 47.729 | M6: 3 | N6: 350.151 | O6: 2 | P6: 0 | Q6: 1 | R6: 86.732 | S6: 1 | T6: 302.667 | U6: 3 | V6: 0.15 | W6: 1 | X6: n.d. | Z6: 1.40 | AA6: 1 | AB6: n.d. | AD6: 11.724 | AE6: 4 | AF6: 933.89 | AG6: 3 | AH6: 1.17 | AI6: 3 | AJ6: 3.50 | AK6: 4
A7: ARCELORMITTAL OLABERRIA-BERGARA SL. | B7: U1 | C7: 2023 | D7: 1.34 | E7: 2 | F7: 46.10 | G7: 5 | H7: 821.642 | I7: 4 | J7: 357.933 | K7: 5 | L7: 78.956 | M7: 1 | N7: 192.929 | O7: 4 | P7: 0 | Q7: 1 | R7: 37.122 | S7: 2 | T7: 157.224 | U7: 5 | V7: 0.15 | W7: 1 | X7: n.d. | Z7: 1.34 | AA7: 2 | AB7: n.d. | AD7: 6.174 | AE7: 5 | AF7: 811.806 | AG7: 4 | AH7: 2.27 | AI7: 1 | AJ7: 8.16 | AK7: 3
A8: GLOBAL STEEL WIRE, SA | B8: U2 | C8: 2023 | D8: 1.09 | E8: 3 | F8: 66.62 | G8: 2 | H8: 580.176 | I8: 5 | J8: 598.15 | K8: 4 | L8: -1.374 | M8: 4 | N8: 199.667 | O8: 3 | P8: 0 | Q8: 1 | R8: 13.981 | S8: 4 | T8: 270.293 | U8: 4 | V8: 0.04 | W8: 3 | X8: n.d. | Z8: 1.09 | AA8: 3 | AB8: n.d. | AD8: 31.112 | AE8: 2 | AF8: 569.362 | AG8: 5 | AH8: 0.95 | AI8: 5 | AJ8: 12.99 | AK8: 1
A9: ACERINOX EUROPA SAU | B9: U1 | C9: 2023 | D9: 0.61 | E9: 4 | F9: 95.34 | G9: 1 | H9: 1,344,692 | I9: 1 | J9: 1,142,438 | K9: 1 | L9: -195.812 | M9: 5 | N9: 53.265 | O9: 5 | P9: 0 | Q9: 1 | R9: 3.449 | S9: 5 | T9: 1,031,409 | U9: 1 | V9: -0.36 | W9: 5 | X9: n.d. | Z9: 0.61 | AA9: 4 | AB9: n.d. | AD9: 39.487 | AE9: 1 | AF9: 1,313,068 | AG9: 1 | AH9: 1.15 | AI9: 4 | AJ9: 3.19 | AK9: 5
A10: COMPAÑIA ESPAÑOLA DE LAMINACION SL | B10: U2 | C10: 2023 | D10: 0.58 | E10: 5 | F10: 57.94 | G10: 3 | H10: 1,162,248 | I10: 2 | J10: 899.098 | K10: 2 | L10: 50.82 | M10: 2 | N10: 378.146 | O10: 1 | P10: 0 | Q10: 1 | R10: 15.759 | S10: 3 | T10: 419.482 | U10: 2 | V10: -0.19 | W10: 4 | X10: n.d. | Z10: 0.58 | AA10: 5 | AB10: n.d. | AD10: 28.019 | AE10: 3 | AF10: 1,160,531 | AG10: 2 | AH10: 1.29 | AI10: 2 | AJ10: 10.54 | AK10: 2
A11: 2022 | E11: Rango | G11: Rango | I11: Rango | K11: Rango | M11: Rango | O11: Rango | Q11: Rango | S11: Rango | U11: Rango | W11: Rango | Y11: Rango | AA11: Rango | AC11: Rango | AE11: Rango | AG11: Rango | AI11: Rango | AK11: Rango
A12: Mediana | D12: 1.12 | F12: 62.02 | H12: 1,089,492 | J12: 849.159 | L12: 47.283 | N12: 242.867 | P12: 0 | R12: 19.009 | T12: 371.013 | V12: 0.06 | X12: n.d. | Z12: 1.12 | AB12: n.d. | AD12: 19.76 | AF12: 1,067,566 | AH12: 1.60 | AJ12: 10.72
A13: Desviación típica | D13: 0.35 | F13: 8.66 | H13: 395.632 | J13: 284.592 | L13: 61.423 | N13: 85.51 | P13: 0 | R13: 45.915 | T13: 250.697 | V13: 0.17 | X13: n.d. | Z13: 0.35 | AB13: n.d. | AD13: 9.274 | AF13: 396.51 | AH13: 0.55 | AJ13: 4.17
A14: Media | D14: 1.08 | F14: 67.02 | H14: 1,251,347 | J14: 763.545 | L14: 42.141 | N14: 240.223 | P14: 0 | R14: 44.355 | T14: 423.5 | V14: 0.02 | X14: n.d. | Z14: 1.08 | AB14: n.d. | AD14: 17.8 | AF14: 1,238,513 | AH14: 1.74 | AJ14: 9.01
A15: ARCELORMITTAL OLABERRIA-BERGARA SL. | B15: U1 | C15: 2022 | D15: 1.56 | E15: 1 | F15: 58.45 | G15: 5 | H15: 1,057,470 | I15: 4 | J15: 374.964 | K15: 5 | L15: 108.649 | M15: 1 | N15: 155.783 | O15: 4 | P15: 0 | Q15: 1 | R15: 57.667 | S15: 2 | T15: 160.55 | U15: 5 | V15: 0.24 | W15: 1 | X15: n.d. | Z15: 1.56 | AA15: 1 | AB15: n.d. | AD15: 2.64 | AE15: 5 | AF15: 1,049,648 | AG15: 4 | AH15: 2.80 | AI15: 1 | AJ15: 10.72 | AK15: 3
A16: SIDENOR ACEROS ESPECIALES SLU | B16: U2 | C16: 2022 | D16: 1.31 | E16: 2 | F16: 62.02 | G16: 3 | H16: 1,089,492 | I16: 3 | J16: 849.159 | K16: 3 | L16: 47.283 | M16: 3 | N16: 322.518 | O16: 2 | P16: 0 | Q16: 1 | R16: 128.244 | S16: 1 | T16: 371.013 | U16: 3 | V16: 0.14 | W16: 2 | X16: n.d. | Z16: 1.31 | AA16: 2 | AB16: n.d. | AD16: 12.601 | AE16: 4 | AF16: 1,067,566 | AG16: 3 | AH16: 1.26 | AI16: 5 | AJ16: 4.19 | AK16: 4
A17: GLOBAL STEEL WIRE, SA | B17: U2 | C17: 2022 | D17: 1.12 | E17: 3 | F17: 75.11 | G17: 2 | H17: 768.035 | I17: 5 | J17: 536.585 | K17: 4 | L17: 16.858 | M17: 4 | N17: 133.554 | O17: 5 | P17: 0 | Q17: 1 | R17: 15.581 | S17: 4 | T17: 276.429 | U17: 4 | V17: 0.06 | W17: 3 | X17: n.d. | Z17: 1.12 | AA17: 3 | AB17: n.d. | AD17: 27.14 | AE17: 1 | AF17: 751.713 | AG17: 5 | AH17: 1.40 | AI17: 4 | AJ17: 11.74 | AK17: 2
A18: ACERINOX EUROPA SAU | B18: U1 | C18: 2022 | D18: 0.83 | E18: 4 | F18: 79.66 | G18: 1 | H18: 1,928,986 | I18: 1 | J18: 1,193,913 | K18: 1 | L18: -60.728 | M18: 5 | N18: 242.867 | O18: 3 | P18: 0 | Q18: 1 | R18: 1.275 | S18: 5 | T18: 893.25 | U18: 1 | V18: -0.13 | W18: 4 | X18: n.d. | Z18: 0.83 | AA18: 4 | AB18: n.d. | AD18: 19.76 | AE18: 3 | AF18: 1,912,676 | AG18: 1 | AH18: 1.60 | AI18: 3 | AJ18: 4.04 | AK18: 5
A19: COMPAÑIA ESPAÑOLA DE LAMINACION SL | B19: U2 | C19: 2022 | D19: 0.57 | E19: 5 | F19: 59.87 | G19: 4 | H19: 1,412,754 | I19: 2 | J19: 863.102 | K19: 2 | L19: 98.645 | M19: 2 | N19: 346.391 | O19: 1 | P19: 0 | Q19: 1 | R19: 19.009 | S19: 3 | T19: 416.257 | U19: 2 | V19: -0.21 | W19: 5 | X19: n.d. | Z19: 0.57 | AA19: 5 | AB19: n.d. | AD19: 26.86 | AE19: 2 | AF19: 1,410,961 | AG19: 2 | AH19: 1.63 | AI19: 2 | AJ19: 14.36 | AK19: 1
A31: Nombre | B31: Código consolidación | C31: Año | D31: Activo no corriente mil EUR | F31: Activo corriente mil EUR | H31: Patrimonio neto mil EUR | J31: Pasivo no corriente mil EUR | L31: Pasivo corriente mil EUR
A32: 2023 | E32: Rango | G32: Rango | I32: Rango | K32: Rango | M32: Rango
A33: Mediana | D33: 375.263 | F33: 294.867 | H33: 199.667 | J33: 101.47 | L33: 302.667
A34: Desviación típica | D34: 174.888 | F34: 151.041 | H34: 118.149 | J34: 50.099 | L34: 309.107
A35: Media | D35: 399.459 | F35: 359.897 | H35: 234.832 | J35: 88.31 | L35: 436.215
A36: COMPAÑIA ESPAÑOLA DE LAMINACION SL | B36: U2 | C36: 2023 | D36: 654.844 | E36: 1 | F36: 244.254 | G36: 4 | H36: 378.146 | I36: 1 | J36: 101.47 | K36: 3 | L36: 419.482 | M36: 2
A37: ACERINOX EUROPA SAU | B37: U1 | C37: 2023 | D37: 517.37 | E37: 2 | F37: 625.068 | G37: 1 | H37: 53.265 | I37: 5 | J37: 57.764 | K37: 4 | L37: 1,031,409 | M37: 1
A38: SIDENOR ACEROS ESPECIALES SLU | B38: U2 | C38: 2023 | D38: 375.263 | E38: 3 | F38: 423.899 | G38: 2 | H38: 350.151 | I38: 2 | J38: 146.344 | K38: 1 | L38: 302.667 | M38: 3
A39: GLOBAL STEEL WIRE, SA | B39: U2 | C39: 2023 | D39: 303.283 | E39: 4 | F39: 294.867 | G39: 3 | H39: 199.667 | I39: 3 | J39: 128.19 | K39: 2 | L39: 270.293 | M39: 4
A40: ARCELORMITTAL OLABERRIA-BERGARA SL. | B40: U1 | C40: 2023 | D40: 146.536 | E40: 5 | F40: 211.397 | G40: 5 | H40: 192.929 | I40: 4 | J40: 7.78 | K40: 5 | L40: 157.224 | M40: 5
A41: 2022 | E41: Rango | G41: Rango | I41: Rango | K41: Rango | M41: Rango
A42: Mediana | D42: 361.466 | F42: 310.524 | H42: 242.867 | J42: 100.454 | L42: 371.013
A43: Desviación típica | D43: 175.106 | F43: 189.206 | H43: 85.51 | J43: 38.196 | L43: 250.697
A44: Media | D44: 358.671 | F44: 404.873 | H44: 240.223 | J44: 99.822 | L44: 423.5
A45: COMPAÑIA ESPAÑOLA DE LAMINACION SL | B45: U2 | C45: 2022 | D45: 625.993 | E45: 1 | F45: 237.109 | G45: 5 | H45: 346.391 | I45: 1 | J45: 100.454 | K45: 3 | L45: 416.257 | M45: 2
A46: ACERINOX EUROPA SAU | B46: U1 | C46: 2022 | D46: 455.451 | E46: 2 | F46: 738.462 | G46: 1 | H46: 242.867 | I46: 3 | J46: 57.796 | K46: 5 | L46: 893.25 | M46: 1
A47: SIDENOR ACEROS ESPECIALES SLU | B47: U2 | C47: 2022 | D47: 361.466 | E47: 3 | F47: 487.693 | G47: 2 | H47: 322.518 | I47: 2 | J47: 155.628 | K47: 1 | L47: 371.013 | M47: 3
A48: GLOBAL STEEL WIRE, SA | B48: U2 | C48: 2022 | D48: 226.061 | E48: 4 | F48: 310.524 | G48: 3 | H48: 133.554 | I48: 5 | J48: 126.602 | K48: 2 | L48: 276.429 | M48: 4
A49: ARCELORMITTAL OLABERRIA-BERGARA SL. | B49: U1 | C49: 2022 | D49: 124.385 | E49: 5 | F49: 250.579 | G49: 4 | H49: 155.783 | I49: 4 | J49: 58.631 | K49: 4 | L49: 160.55 | M49: 5

Sheet COMPARATIVA SECTORIAL
A1: COMPARATIVA SECTORIAL — ACERINOX EUROPA, S.A.U.
C3: ACERINOX — 2023 | S3: SECTOR — 2022 | AC3: ACERINOX 2023 — datos chart
AD4: Pasivo C | AE4: Pasivo NC | AF4: Patrimonio Neto | AG4: Activo Corriente | AH4: Activo No Corriente | AI4: Base FM (oculta) | AJ4: Fondo de Maniobra
AC5: Activo | AD5: 0 | AE5: 0 | AF5: 0 | AG5: =D8 -> 625068 | AH5: =D7 -> 517370 | AI5: 0 | AJ5: 0
D6: Total (miles €) | E6: Desglose | F6: PN + Pasivo (miles €) | AC6: FM | AD6: 0 | AE6: 0 | AF6: 0 | AG6: 0 | AH6: 0 | AI6: =F7+F8 -> 111029 | AJ6: =ABS(D8-F9) -> 406341
C7: Activo nc | D7: ='BALANCE DE SITUACIÓN'!C3 -> 517370 | E7: =D7 -> 517370 | F7: ='BALANCE DE SITUACIÓN'!C84 -> 53265 | G7: Patrimonio | T7: Total (miles €) | U7: Desglose | V7: PN + Pasivo (miles €) | AC7: PN + Pasivo | AD7: =F9 -> 1031409 | AE7: =F8 -> 57764 | AF7: =F7 -> 53265 | AG7: 0 | AH7: 0 | AI7: 0 | AJ7: 0
C8: Activo c | D8: ='BALANCE DE SITUACIÓN'!C36 -> 625068 | E8: =F7+F8-D7 -> -406341 | F8: ='BALANCE DE SITUACIÓN'!C110 -> 57764 | G8: Pasivo nc | S8: Activo nc | T8: ='DATOS SECTOR'!D44*1000 -> 358671 | U8: =T8 -> 358671 | V8: ='DATOS SECTOR'!H44*1000 -> 240223 | W8: Patrimonio
F9: ='BALANCE DE SITUACIÓN'!C127 -> 1031409 | G9: Pasivo c | S9: Activo c | T9: ='DATOS SECTOR'!F44*1000 -> 404873 | U9: =V8+V9-T8 -> -18626 | V9: ='DATOS SECTOR'!J44*1000 -> 99822 | W9: Pasivo nc
V10: ='DATOS SECTOR'!L44*1000 -> 423500 | W10: Pasivo c | AC10: ACERINOX 2022 — datos chart
AD11: Pasivo C | AE11: Pasivo NC | AF11: Patrimonio Neto | AG11: Activo Corriente | AH11: Activo No Corriente | AI11: Base FM (oculta) | AJ11: Fondo de Maniobra
AC12: Activo | AD12: 0 | AE12: 0 | AF12: 0 | AG12: =D37 -> 738462 | AH12: =D36 -> 455451 | AI12: 0 | AJ12: 0
AC13: FM | AD13: 0 | AE13: 0 | AF13: 0 | AG13: 0 | AH13: 0 | AI13: =F36+F37 -> 300663 | AJ13: =ABS(D37-F38) -> 154788
AC14: PN + Pasivo | AD14: =F38 -> 893250 | AE14: =F37 -> 57796 | AF14: =F36 -> 242867 | AG14: 0 | AH14: 0 | AI14: 0 | AJ14: 0
AC17: SECTOR 2022 — datos chart
AD18: Pasivo C | AE18: Pasivo NC | AF18: Patrimonio Neto | AG18: Activo Corriente | AH18: Activo No Corriente | AI18: Base FM (oculta) | AJ18: Fondo de Maniobra
AC19: Activo | AD19: 0 | AE19: 0 | AF19: 0 | AG19: =T9 -> 404873 | AH19: =T8 -> 358671 | AI19: 0 | AJ19: 0
AC20: FM | AD20: 0 | AE20: 0 | AF20: 0 | AG20: 0 | AH20: 0 | AI20: =V8+V9 -> 340045 | AJ20: =ABS(T9-V10) -> 18627
AC21: PN + Pasivo | AD21: =V10 -> 423500 | AE21: =V9 -> 99822 | AF21: =V8 -> 240223 | AG21: 0 | AH21: 0 | AI21: 0 | AJ21: 0
AC24: SECTOR 2023 — datos chart
AD25: Pasivo C | AE25: Pasivo NC | AF25: Patrimonio Neto | AG25: Activo Corriente | AH25: Activo No Corriente | AI25: Base FM (oculta) | AJ25: Fondo de Maniobra
AC26: Activo | AD26: 0 | AE26: 0 | AF26: 0 | AG26: =T39 -> 359897 | AH26: =T38 -> 399459 | AI26: 0 | AJ26: 0
AC27: FM | AD27: 0 | AE27: 0 | AF27: 0 | AG27: 0 | AH27: 0 | AI27: =V38+V39 -> 323142 | AJ27: =ABS(T39-V40) -> 76318
AC28: PN + Pasivo | AD28: =V40 -> 436215 | AE28: =V39 -> 88310 | AF28: =V38 -> 234832 | AG28: 0 | AH28: 0 | AI28: 0 | AJ28: 0
C33: ACERINOX — 2022 | S33: SECTOR — 2023
D35: Total (miles €) | E35: Desglose | F35: PN + Pasivo (miles €)
C36: Activo nc | D36: ='BALANCE DE SITUACIÓN'!D3 -> 455451 | E36: =D36 -> 455451 | F36: ='BALANCE DE SITUACIÓN'!D84 -> 242867 | G36: Patrimonio
C37: Activo c | D37: ='BALANCE DE SITUACIÓN'!D36 -> 738462 | E37: =F36+F37-D36 -> -154788 | F37: ='BALANCE DE SITUACIÓN'!D110 -> 57796 | G37: Pasivo nc | T37: Total (miles €) | U37: Desglose | V37: PN + Pasivo (miles €)
F38: ='BALANCE DE SITUACIÓN'!D127 -> 893250 | G38: Pasivo c | S38: Activo nc | T38: ='DATOS SECTOR'!D35*1000 -> 399459 | U38: =T38 -> 399459 | V38: ='DATOS SECTOR'!H35*1000 -> 234832 | W38: Patrimonio
S39: Activo c | T39: ='DATOS SECTOR'!F35*1000 -> 359897 | U39: =V38+V39-T38 -> -76317 | V39: ='DATOS SECTOR'!J35*1000 -> 88310 | W39: Pasivo nc
V40: ='DATOS SECTOR'!L35*1000 -> 436215 | W40: Pasivo c

Sheet ANÁLISIS PATRIMONIAL
A1: ANÁLISIS DE LA SITUACIÓN PATRIMONIAL — ACERINOX EUROPA, S.A.U.
A3: 1. ORDENACIÓN DEL BALANCE | H3: Categoría | I3: ANC | J3: AC | K3: PN | L3: PNC | M3: PC
A4: MASA PATRIMONIAL | B4: 2022 (miles €) | C4: 2023 (miles €) | D4: Var. Absoluta | E4: Var. Relativa (%) | F4: Tendencia | H4: Activo 2022 | I4: =B5 -> 455451 | J4: =B6 -> 738462 | K4: 0 | L4: 0 | M4: 0
A5: Activo No Corriente (ANC) | B5: ='BALANCE DE SITUACIÓN'!D3 -> 455451 | C5: ='BALANCE DE SITUACIÓN'!C3 -> 517370 | D5: =C5-B5 -> 61919 | E5: =IF(B5=0,"-",D5/B5) -> 0.13595096 | F5: =IF(D5>0,"Sube",IF(D5<0,"Baja","Igual")) -> Sube | H5: PN+P 2022 | I5: 0 | J5: 0 | K5: =B8 -> 242867 | L5: =B9 -> 57796 | M5: =B10 -> 893250
A6: Activo Corriente (AC) | B6: ='BALANCE DE SITUACIÓN'!D36 -> 738462 | C6: ='BALANCE DE SITUACIÓN'!C36 -> 625068 | D6: =C6-B6 -> -113394 | E6: =IF(B6=0,"-",D6/B6) -> -0.15355428 | F6: =IF(D6>0,"Sube",IF(D6<0,"Baja","Igual")) -> Baja | H6: Activo 2023 | I6: =C5 -> 517370 | J6: =C6 -> 625068 | K6: 0 | L6: 0 | M6: 0
A7: TOTAL ACTIVO | B7: =B5+B6 -> 1193913 | C7: =C5+C6 -> 1142438 | D7: =C7-B7 -> -51475 | E7: =IF(B7=0,"-",D7/B7) -> -0.043114532 | H7: PN+P 2023 | I7: 0 | J7: 0 | K7: =C8 -> 53265 | L7: =C9 -> 57764 | M7: =C10 -> 1031409
A8: Patrimonio Neto (PN) | B8: ='BALANCE DE SITUACIÓN'!D84 -> 242867 | C8: ='BALANCE DE SITUACIÓN'!C84 -> 53265 | D8: =C8-B8 -> -189602 | E8: =IF(B8=0,"-",D8/B8) -> -0.78068243 | F8: =IF(D8>0,"Sube",IF(D8<0,"Baja","Igual")) -> Baja
A9: Pasivo No Corriente (PNC) | B9: ='BALANCE DE SITUACIÓN'!D110 -> 57796 | C9: ='BALANCE DE SITUACIÓN'!C110 -> 57764 | D9: =C9-B9 -> -32 | E9: =IF(B9=0,"-",D9/B9) -> -0.00055367153 | F9: =IF(D9>0,"Sube",IF(D9<0,"Baja","Igual")) -> Baja
A10: Pasivo Corriente (PC) | B10: ='BALANCE DE SITUACIÓN'!D127 -> 893250 | C10: ='BALANCE DE SITUACIÓN'!C127 -> 1031409 | D10: =C10-B10 -> 138159 | E10: =IF(B10=0,"-",D10/B10) -> 0.15467003 | F10: =IF(D10>0,"Sube",IF(D10<0,"Baja","Igual")) -> Sube
A11: TOTAL PN + PASIVO | B11: =B8+B9+B10 -> 1193913 | C11: =C8+C9+C10 -> 1142438 | D11: =C11-B11 -> -51475 | E11: =IF(B11=0,"-",D11/B11) -> -0.043114532
A13: 2. ESTRUCTURA PORCENTUAL
A14: MASA PATRIMONIAL | B14: 2022 | C14: 2023 | D14: Variación (p.p.)
A15: Activo No Corriente | B15: =B5/B7 -> 0.38147754 | C15: =C5/C7 -> 0.45286484 | D15: =C15-B15 -> 0.071387293
A16: Activo Corriente | B16: =B6/B7 -> 0.61852246 | C16: =C6/C7 -> 0.54713516 | D16: =C16-B16 -> -0.071387293
A17: TOTAL ACTIVO | B17: =B15+B16 -> 1 | C17: =C15+C16 -> 1
A18: Patrimonio Neto | B18: =B8/B11 -> 0.20342102 | C18: =C8/C11 -> 0.046623974 | D18: =C18-B18 -> -0.15679705
A19: Pasivo No Corriente | B19: =B9/B11 -> 0.048408887 | C19: =C9/C11 -> 0.050562044 | D19: =C19-B19 -> 0.0021531562
A20: Pasivo Corriente | B20: =B10/B11 -> 0.74817009 | C20: =C10/C11 -> 0.90281398 | D20: =C20-B20 -> 0.15464389
A21: TOTAL PN + PASIVO | B21: =B18+B19+B20 -> 1 | C21: =C18+C19+C20 -> 1
A23: 3. FONDO DE MANIOBRA
A24: CONCEPTO | B24: 2022 | C24: 2023 | D24: Variación
A25: Activo Corriente | B25: =B6 -> 738462 | C25: =C6 -> 625068 | D25: =C25-B25 -> -113394
A26: (-) Pasivo Corriente | B26: =B10 -> 893250 | C26: =C10 -> 1031409 | D26: =C26-B26 -> 138159
A27: = FONDO DE MANIOBRA | B27: =B25-B26 -> -154788 | C27: =C25-C26 -> -406341 | D27: =C27-B27 -> -251553
A28: FM / Activo Total | B28: =B27/B7 -> -0.12964764 | C28: =C27/C7 -> -0.35567882
A29: FM / Pasivo Corriente | B29: =B27/B10 -> -0.17328631 | C29: =C27/C10 -> -0.39396689
A31: INTERPRETACIÓN
A32: Ordenación y Variaciones: | B32: El Activo Total disminuye un 4,31% (de 1.193.913 a 1.142.438 miles €). El ANC crece un 13,59%, mientras que el AC cae un 15,36% por la reducción de clientes grupo (-101.718 miles €) y existencias (-56.651 miles €). En el lado de la financiación, el PN se desploma un 78,08% por las pérdidas de -195,8 M€, y el PC crece un 15,47% hasta superar los 1.031 M€, absorbiendo el 90% de la financiación total.
A33: Estructura Porcentual: | B33: La estructura patrimonial está gravemente desequilibrada. En 2023, el PN apenas representa el 4,66% del total (frente al 20,34% de 2022), mientras que el PC supone el 90,28%. La empresa financia prácticamente todo su activo con deuda a corto plazo, lo cual es una señal de alarma crítica para cualquier acreedor. La capitalización se ha erosionado por las pérdidas acumuladas.
A34: Fondo de Maniobra: | B34: El FM es negativo en ambos ejercicios y empeora drásticamente: de -154.788 miles € (2022) a -406.341 miles € (2023). Esto significa que los recursos permanentes (PN + PNC = 111.029 miles €) no cubren ni el 21% del ANC (517.370 miles €). La empresa depende críticamente de las líneas de crédito intragrupo con Acerinox, S.A. (532.208 miles € en deuda con grupo a c/p). Sin este apoyo de la matriz, la empresa sería técnicamente insolvente a corto plazo.
A35: Conclusión: | B35: Acerinox Europa presenta una situación patrimonial de riesgo elevado. La empresa ha pasado de una situación patrimonial ya débil en 2022 a una posición crítica en 2023. La viabilidad como empresa en funcionamiento (going concern) depende exclusivamente del compromiso continuado de financiación de su socio único, Acerinox S.A.
A40: 1.bis — DESGLOSE DEL ACTIVO CORRIENTE (modelo 7 masas Tema 3)
A41: MASA PATRIMONIAL | B41: 2022 (miles €) | C41: 2023 (miles €) | D41: Var. Absoluta | E41: Var. Relativa (%) | F41: % s/ Total Activo 2023
A42: Activo No Corriente (ANC) | B42: ='BALANCE DE SITUACIÓN'!D3 -> 455451 | C42: ='BALANCE DE SITUACIÓN'!C3 -> 517370 | D42: =C42-B42 -> 61919 | E42: =IF(B42=0,"-",D42/B42) -> 0.13595096 | F42: =C42/$C$46 -> 0.45286484
A43: Existencias | B43: ='BALANCE DE SITUACIÓN'!D38 -> 477896 | C43: ='BALANCE DE SITUACIÓN'!C38 -> 421245 | D43: =C43-B43 -> -56651 | E43: =IF(B43=0,"-",D43/B43) -> -0.11854253 | F43: =C43/$C$46 -> 0.3687246
A44: Realizable | B44: ='BALANCE DE SITUACIÓN'!D51+'BALANCE DE SITUACIÓN'!D61+'BALANCE DE SITUACIÓN'!D68+'BALANCE DE SITUACIÓN'!D75 -> 259291 | C44: ='BALANCE DE SITUACIÓN'!C51+'BALANCE DE SITUACIÓN'!C61+'BALANCE DE SITUACIÓN'!C68+'BALANCE DE SITUACIÓN'!C75 -> 200374 | D44: =C44-B44 -> -58917 | E44: =IF(B44=0,"-",D44/B44) -> -0.22722347 | F44: =C44/$C$46 -> 0.17539157
A45: Efectivo y equivalentes | B45: ='BALANCE DE SITUACIÓN'!D76 -> 1275 | C45: ='BALANCE DE SITUACIÓN'!C76 -> 3449 | D45: =C45-B45 -> 2174 | E45: =IF(B45=0,"-",D45/B45) -> 1.705098 | F45: =C45/$C$46 -> 0.0030189822
A46: TOTAL ACTIVO | B46: =B42+B43+B44+B45 -> 1193913 | C46: =C42+C43+C44+C45 -> 1142438 | D46: =C46-B46 -> -51475 | E46: =IF(B46=0,"-",D46/B46) -> -0.043114532 | F46: =C46/$C$46 -> 1

Sheet ANÁLISIS ENDEUDAMIENTO
A1: ANÁLISIS DE ENDEUDAMIENTO — ACERINOX EUROPA, S.A.U.
B2: 2022 | C2: 2023 | D2: REFERENCIA | E2: ANÁLISIS 2022 | F2: ANÁLISIS 2023
A3: RATIO DE ENDEUDAMIENTO | B3: =RATIOS!B9 -> 0.79657898 | C3: =RATIOS!C9 -> 0.95337603 | D3: 0,4 < R.e. < 0,6 | E3: Hay una deuda excesiva, la empresa no puede soportar la carga financiera de ésta y va a perder su autonomía financiera, hay riesgo de descapitalización. | F3: La situación es peor que en el 2022, entonces hay una deuda excesiva, la empresa no puede soportar la carga financiera de ésta y va a perder su autonomía financiera, hay riesgo de descapitalización.
A4: RATIO DE AUTONOMÍA | B4: =RATIOS!B10 -> 0.2553683 | C4: =RATIOS!C10 -> 0.048904077 | D4: 0,7 < R.a. < 1,5 | E4: La empresa tiene una deuda excesiva, depende demasiado de la financiación externa, sufre una pérdida de autonomía financiera. | F4: La situación tiene los mismos riesgos que en 2022, pero en este caso es mucho peor: de hecho, en 2023 por cada euro de deuda la empresa tiene menos de 5 céntimos propios.
A5: RATIO DE SOLVENCIA O GARANTÍA | B5: =RATIOS!B11 -> 1.2553683 | C5: =RATIOS!C11 -> 1.0489041 | D5: R.s. ≈ 1,5 (>1) | E5: La empresa se encuentra en una situación de riesgo: si alguno de sus activos pierde valor, podría no poder pagar sus deudas. | F5: La empresa está muy cerca de la quiebra técnica, ya que debe más de lo que posee, lo que compromete su capacidad de continuar con la actividad comercial.
A6: RATIO DE CALIDAD DE LA DEUDA | B6: =RATIOS!B12 -> 0.93922902 | C6: =RATIOS!C12 -> 0.94696527 | D6: más bajo posible | E6: La calidad de la deuda es muy mala: el 93,9% de la deuda total es a corto plazo, lo que indica una presión financiera muy elevada a corto plazo y un riesgo significativo de impago. | F6: La situación empeora en 2023: el 94,7% de la deuda es a corto plazo frente al 93,9% de 2022. La concentración de deuda a corto plazo sigue siendo excesiva y aumenta el riesgo de tensiones de liquidez.
A7: RATIO DE GASTOS FINANCIEROS SOBRE VENTAS | B7: =RATIOS!B13 -> 0.0084993726 | C7: =RATIOS!C13 -> 0.030033658 | D7: < 0,04 | E7: El ratio se sitúa en el 0,85%, muy por debajo del umbral de alarma del 5%. Los gastos financieros son reducidos en relación a las ventas, lo que es un aspecto positivo. | F7: El ratio se deteriora significativamente, pasando del 0,85% al 3,00% en 2023. Aunque sigue por debajo del 5%, el aumento es muy notable y refleja el incremento de los gastos financieros y la caída de las ventas.
A8: RATIO DE COSTE DE LA DEUDA | B8: =RATIOS!B14 -> 0.023080258 | C8: =RATIOS!C14 -> 0.049912425 | D8: < coste medio del dinero | E8: El coste medio de la deuda con coste se sitúa en torno al 2,3%, valor reducido y coherente con la fuerte presencia de financiación intragrupo (preferencial). Muy por debajo del coste medio del dinero del Banco de España (≈3,25%). | F8: El coste sube hasta el 5,0%, todavía moderado pero con incremento significativo (+2,7 p.p.) por el mayor recurso a deuda con entidades de crédito y empresas del grupo, en un entorno de tipos altos. Sigue ligeramente por encima del coste medio del dinero del BCE.
A9: COBERTURA DE GASTOS FINANCIEROS | B9: =RATIOS!B15 -> NO CUBRE (BAII negativo) | C9: =RATIOS!C15 -> NO CUBRE (BAII negativo) | D9: > 2 | E9: El BAII de la empresa es negativo: no hay beneficio, por lo que los gastos financieros no se pueden cubrir. | F9: El BAII de la empresa es negativo: no hay beneficio, por lo que los gastos financieros no se pueden cubrir.

Sheet ANÁLISIS LIQUIDEZ
A1: ANÁLISIS DE LIQUIDEZ — ACERINOX EUROPA, S.A.U.
B2: 2022 | C2: 2023 | D2: REFERENCIA | E2: ANÁLISIS 2022 | F2: ANÁLISIS 2023
A3: RATIO DE LIQUIDEZ | B3: =RATIOS!B3 -> 0.82671369 | C3: =RATIOS!C3 -> 0.60603311 | D3: 1,5 < R.l. < 2 | E3: Es menor que 1,5, así que la empresa presenta posibles problemas de liquidez. | F3: Es menor que 1,5 así que la empresa mantiene posibles problemas de liquidez, en este caso de forma aún más acusada que en 2022, ya que el ratio desciende de 0,827 a 0,606.
A4: RATIO DE TESORERÍA | B4: =RATIOS!B4 -> 0.29170557 | C4: =RATIOS!C4 -> 0.19761608 | D4: R.t. ≈ 1 | E4: El ratio de tesorería es de 0,292 , muy por debajo de 1. Esto significa que si descontamos las existencias, la empresa apenas puede cubrir el 29% de su pasivo corriente con activos líquidos. La situación es preocupante y revela una fuerte dependencia de la venta de existencias para atender sus obligaciones a corto plazo. | F4: El ratio de tesorería cae a 0,20, empeorando frente al de 2022. Sin las existencias, la empresa solo puede cubrir el 20% de su pasivo corriente. La situación de liquidez se deteriora significativamente.
A5: RATIO DE DISPONIBILIDAD | B5: =RATIOS!B5 -> 0.001427372 | C5: =RATIOS!C5 -> 0.0033439693 | D5: R.d. ≈ 0,2 - 0,3 | E5: El ratio de disponibilidad es prácticamente nulo 0,001, lo que indica que la empresa no dispone de efectivo inmediato para hacer frente a sus deudas a corto plazo. La tesorería es de apenas 1.275 miles € frente a un pasivo corriente de 893.250 miles €. | F5: El ratio de disponibilidad sigue siendo prácticamente nulo, aunque mejora ligeramente respecto a 2022, el efectivo disponible (3.449 miles €) es absolutamente insuficiente frente a un pasivo corriente de más de 1 millón de miles €.
A6: RATIO DE F.M SOBRE ACTIVO | B6: =RATIOS!B6 -> -0.12964764 | C6: =RATIOS!C6 -> -0.35567882 | D6: positivo (> 0) | E6: Al tener un FM negativo nos indica que la empresa tiene una posibilidad razonable de insolvencia. | F6: Sigue teniendo un FM negativo lo cual nos indica que la empresa tiene una posibilidad razonable de insolvencia. Este año el problema es aún mayor al ser el ratio aún más negativo.
A7: RATIO DE F.M SOBRE PASIVO CORRENTE | B7: =RATIOS!B7 -> -0.17328631 | C7: =RATIOS!C7 -> -0.39396689 | D7: positivo (> 0) | E7: El FM sobre pasivo corriente es -0,173, lo que confirma que el fondo de maniobra negativo representa un 17,3% del pasivo corriente. La empresa necesita refinanciar parte de su deuda a corto plazo o incrementar sus recursos permanentes. | F7: El FM sobre pasivo corriente empeora a -0,394, lo que significa que el déficit de fondo de maniobra ya representa casi el 40% del pasivo corriente, frente al 17,3% de 2022. La dependencia de financiación a corto plazo es cada vez más crítica.

Sheet ANÁLISIS EOAF
A1: ESTADO DE ORIGEN Y APLICACIÓN DE FONDOS (EOAF) — ACERINOX EUROPA, S.A.U.
A3: 1. VARIACIONES DEL BALANCE (2022 → 2023, miles €)
A4: MASA PATRIMONIAL | B4: 2022 (miles €) | C4: 2023 (miles €) | D4: Variación | E4: Clasificación
A5: ANC (bruto = neto + amort. período) | B5: ='BALANCE DE SITUACIÓN'!D3 -> 455451 | C5: ='BALANCE DE SITUACIÓN'!C3 -> 517370 | D5: =(C5-B5)+C6 -> 97922 | E5: =IF(D5>0,"Aplicación l/p",IF(D5<0,"Origen l/p","-")) -> Aplicación l/p
A6: Amortización del período | B6: =ABS('CUENTA DE PÉRDIDAS Y GANANCIAS'!D28) -> 30024 | C6: =ABS('CUENTA DE PÉRDIDAS Y GANANCIAS'!C28) -> 36003 | E6: Origen l/p (siempre)
A7: PN (var. total sin resultado N) | B7: ='BALANCE DE SITUACIÓN'!D84 -> 242867 | C7: ='BALANCE DE SITUACIÓN'!C84 -> 53265 | D7: =(C7-B7)-'BALANCE DE SITUACIÓN'!C100 -> 6210 | E7: =IF(D7>0,"Origen l/p",IF(D7<0,"Aplicación l/p","-")) -> Origen l/p
A8: Resultado del ejercicio 2023 | C8: ='BALANCE DE SITUACIÓN'!C100 -> -195812 | D8: =C8 -> -195812 | E8: =IF(C8>=0,"Origen l/p (beneficio)","Aplicación l/p (pérdidas)") -> Aplicación l/p (pérdidas)
A9: Pasivo No Corriente (PNC) | B9: ='BALANCE DE SITUACIÓN'!D110 -> 57796 | C9: ='BALANCE DE SITUACIÓN'!C110 -> 57764 | D9: =C9-B9 -> -32 | E9: =IF(D9>0,"Origen l/p",IF(D9<0,"Aplicación l/p","-")) -> Aplicación l/p
A10: Existencias | B10: ='BALANCE DE SITUACIÓN'!D38 -> 477896 | C10: ='BALANCE DE SITUACIÓN'!C38 -> 421245 | D10: =C10-B10 -> -56651 | E10: =IF(D10>0,"Aplicación c/p",IF(D10<0,"Origen c/p","-")) -> Origen c/p
A11: Realizable | B11: ='BALANCE DE SITUACIÓN'!D51+'BALANCE DE SITUACIÓN'!D61+'BALANCE DE SITUACIÓN'!D68+'BALANCE DE SITUACIÓN'!D75 -> 259291 | C11: ='BALANCE DE SITUACIÓN'!C51+'BALANCE DE SITUACIÓN'!C61+'BALANCE DE SITUACIÓN'!C68+'BALANCE DE SITUACIÓN'!C75 -> 200374 | D11: =C11-B11 -> -58917 | E11: =IF(D11>0,"Aplicación c/p",IF(D11<0,"Origen c/p","-")) -> Origen c/p
A12: Efectivo | B12: ='BALANCE DE SITUACIÓN'!D76 -> 1275 | C12: ='BALANCE DE SITUACIÓN'!C76 -> 3449 | D12: =C12-B12 -> 2174 | E12: =IF(D12>0,"Aplicación c/p",IF(D12<0,"Origen c/p","-")) -> Aplicación c/p
A13: Pasivo Corriente (PC) | B13: ='BALANCE DE SITUACIÓN'!D127 -> 893250 | C13: ='BALANCE DE SITUACIÓN'!C127 -> 1031409 | D13: =C13-B13 -> 138159 | E13: =IF(D13>0,"Origen c/p",IF(D13<0,"Aplicación c/p","-")) -> Origen c/p
A15: 2. ESTADO DE ORIGEN Y APLICACIÓN DE FONDOS (miles €)
B16: APLICACIÓN | C16: (miles €) | E16: ORIGEN | F16: (miles €)
A17: l/p | B17: Activo No Corriente | C17: =ABS(D5) -> 97922 | E17: Patrimonio Neto | F17: =ABS(D7) -> 6210
B18: Pasivo No Corriente | C18: =ABS(D9) -> 32 | E18: Amortización del período | F18: =C6 -> 36003
B19: Pérdidas del ejercicio | C19: =ABS(D8) -> 195812 | E19: Var. Fondo de Maniobra | F19: =SUM(C17:C19)-SUM(F17:F18) -> 251553
A21: c/p | B21: Efectivo | C21: =ABS(D12) -> 2174 | E21: Existencias | F21: =ABS(D10) -> 56651
E22: Realizable | F22: =ABS(D11) -> 58917
E23: Pasivo Corriente | F23: =ABS(D13) -> 138159
B24: TOTAL | C24: =SUM(C17:C19)+SUM(C21:C21) -> 295940 | E24: TOTAL | F24: =SUM(F17:F18)+SUM(F21:F23) -> 295940

Sheet ANÁLISIS CUENTA PyG
A1: ANÁLISIS DE LA CUENTA DE PÉRDIDAS Y GANANCIAS — ACERINOX EUROPA, S.A.U.
A3: 6.1. CUENTA DE PyG ANALÍTICA: VALORES ABSOLUTOS Y PORCENTAJES
A5: CONCEPTO | B5: 2023 (miles €) | C5: 2022 (miles €) | D5: % s/Ventas 2023 | E5: % s/Ventas 2022 | F5: Variación absoluta | G5: Variación %
A6: Ventas (Importe neto cifra de negocios) | B6: ='CUENTA DE PÉRDIDAS Y GANANCIAS'!C4 -> 1313068 | C6: ='CUENTA DE PÉRDIDAS Y GANANCIAS'!D4 -> 1912676 | D6: =B6/$B$6 -> 1 | E6: =C6/$C$6 -> 1 | F6: =B6-C6 -> -599608 | G6: =IFERROR(F6/ABS(C6),"n/a") -> -0.31349167
A7: (-) Coste de ventas (Aprovisionam. ± Var. exist. + Trabajos activo) | B7: ='CUENTA DE PÉRDIDAS Y GANANCIAS'!C10+'CUENTA DE PÉRDIDAS Y GANANCIAS'!C8+'CUENTA DE PÉRDIDAS Y GANANCIAS'!C9 -> -1164466 | C7: ='CUENTA DE PÉRDIDAS Y GANANCIAS'!D10+'CUENTA DE PÉRDIDAS Y GANANCIAS'!D8+'CUENTA DE PÉRDIDAS Y GANANCIAS'!D9 -> -1414210 | D7: =B7/$B$6 -> -0.8868284 | E7: =C7/$C$6 -> -0.73938817 | F7: =B7-C7 -> 249744 | G7: =IFERROR(F7/ABS(C7),"n/a") -> 0.17659612
A8: = MARGEN BRUTO | B8: =B6+B7 -> 148602 | C8: =C6+C7 -> 498466 | D8: =B8/$B$6 -> 0.1131716 | E8: =C8/$C$6 -> 0.26061183 | F8: =B8-C8 -> -349864 | G8: =IFERROR(F8/ABS(C8),"n/a") -> -0.70188137
A9: (-) Otros gastos de explotación (excepto amort. y deterioro) | B9: ='CUENTA DE PÉRDIDAS Y GANANCIAS'!C22 -> -245240 | C9: ='CUENTA DE PÉRDIDAS Y GANANCIAS'!D22 -> -425170 | D9: =B9/$B$6 -> -0.1867687 | E9: =C9/$C$6 -> -0.22229065 | F9: =B9-C9 -> 179930 | G9: =IFERROR(F9/ABS(C9),"n/a") -> 0.42319543
A10: (+) Otros ingresos de explotación | B10: ='CUENTA DE PÉRDIDAS Y GANANCIAS'!C15+'CUENTA DE PÉRDIDAS Y GANANCIAS'!C29 -> 32796 | C10: ='CUENTA DE PÉRDIDAS Y GANANCIAS'!D15+'CUENTA DE PÉRDIDAS Y GANANCIAS'!D29 -> 16527 | D10: =B10/$B$6 -> 0.02497662 | E10: =C10/$C$6 -> 0.0086407735 | F10: =B10-C10 -> 16269 | G10: =IFERROR(F10/ABS(C10),"n/a") -> 0.98438918
A11: = VALOR AÑADIDO BRUTO (VAB) | B11: =B8+B9+B10 -> -63842 | C11: =C8+C9+C10 -> 89823 | D11: =B11/$B$6 -> -0.048620483 | E11: =C11/$C$6 -> 0.046961953 | F11: =B11-C11 -> -153665 | G11: =IFERROR(F11/ABS(C11),"n/a") -> -1.7107534
A12: (-) Gastos de personal | B12: ='CUENTA DE PÉRDIDAS Y GANANCIAS'!C18 -> -124720 | C12: ='CUENTA DE PÉRDIDAS Y GANANCIAS'!D18 -> -129817 | D12: =B12/$B$6 -> -0.094983657 | E12: =C12/$C$6 -> -0.067871924 | F12: =B12-C12 -> 5097 | G12: =IFERROR(F12/ABS(C12),"n/a") -> 0.039262962
A13: = EBITDA (Rdo. bruto de explotación) | B13: =B11+B12 -> -188562 | C13: =C11+C12 -> -39994 | D13: =B13/$B$6 -> -0.14360414 | E13: =C13/$C$6 -> -0.020909971 | F13: =B13-C13 -> -148568 | G13: =IFERROR(F13/ABS(C13),"n/a") -> -3.7147572
A14: (-) Amortizaciones | B14: ='CUENTA DE PÉRDIDAS Y GANANCIAS'!C28 -> -36003 | C14: ='CUENTA DE PÉRDIDAS Y GANANCIAS'!D28 -> -30024 | D14: =B14/$B$6 -> -0.027418991 | E14: =C14/$C$6 -> -0.015697379 | F14: =B14-C14 -> -5979 | G14: =IFERROR(F14/ABS(C14),"n/a") -> -0.19914069
A15: (-) Deterioro y otros | B15: ='CUENTA DE PÉRDIDAS Y GANANCIAS'!C31 -> -411 | C15: ='CUENTA DE PÉRDIDAS Y GANANCIAS'!D31 -> -241 | D15: =B15/$B$6 -> -0.0003130074 | E15: =C15/$C$6 -> -0.00012600148 | F15: =B15-C15 -> -170 | G15: =IFERROR(F15/ABS(C15),"n/a") -> -0.70539419
A16: = BAII (Rdo. neto de explotación ≡ EBIT) | B16: =B13+B14+B15 -> -224976 | C16: =C13+C14+C15 -> -70259 | D16: =B16/$B$6 -> -0.17133614 | E16: =C16/$C$6 -> -0.036733352 | F16: =B16-C16 -> -154717 | G16: =IFERROR(F16/ABS(C16),"n/a") -> -2.2020951
A17: (+) Ingresos financieros | B17: ='CUENTA DE PÉRDIDAS Y GANANCIAS'!C38 -> 350 | C17: ='CUENTA DE PÉRDIDAS Y GANANCIAS'!D38 -> 1903 | D17: =B17/$B$6 -> 0.00026655131 | E17: =C17/$C$6 -> 0.00099494112 | F17: =B17-C17 -> -1553 | G17: =IFERROR(F17/ABS(C17),"n/a") -> -0.81607987
A18: (-) Gastos financieros | B18: ='CUENTA DE PÉRDIDAS Y GANANCIAS'!C46 -> -39155 | C18: ='CUENTA DE PÉRDIDAS Y GANANCIAS'!D46 -> -16235 | D18: =B18/$B$6 -> -0.029819476 | E18: =C18/$C$6 -> -0.0084881078 | F18: =B18-C18 -> -22920 | G18: =IFERROR(F18/ABS(C18),"n/a") -> -1.4117647
A19: (+/-) Otros ingresos y gastos financieros | B19: ='CUENTA DE PÉRDIDAS Y GANANCIAS'!C50+'CUENTA DE PÉRDIDAS Y GANANCIAS'!C53 -> 1311 | C19: ='CUENTA DE PÉRDIDAS Y GANANCIAS'!D50+'CUENTA DE PÉRDIDAS Y GANANCIAS'!D53 -> 1375 | D19: =B19/$B$6 -> 0.00099842506 | E19: =C19/$C$6 -> 0.00071888809 | F19: =B19-C19 -> -64 | G19: =IFERROR(F19/ABS(C19),"n/a") -> -0.046545455
A20: = BAI (Bº antes de impuestos) | B20: =B16+B17+B18+B19 -> -262470 | C20: =C16+C17+C18+C19 -> -83216 | D20: =B20/$B$6 -> -0.19989064 | E20: =C20/$C$6 -> -0.04350763 | F20: =B20-C20 -> -179254 | G20: =IFERROR(F20/ABS(C20),"n/a") -> -2.1540809
A21: (-) Impuesto sobre beneficios | B21: ='CUENTA DE PÉRDIDAS Y GANANCIAS'!C63 -> 66658 | C21: ='CUENTA DE PÉRDIDAS Y GANANCIAS'!D63 -> 22488 | D21: =B21/$B$6 -> 0.050765078 | E21: =C21/$C$6 -> 0.011757349 | F21: =B21-C21 -> 44170 | G21: =IFERROR(F21/ABS(C21),"n/a") -> 1.9641587
A22: = RESULTADO DEL EJERCICIO | B22: =B20+B21 -> -195812 | C22: =C20+C21 -> -60728 | D22: =B22/$B$6 -> -0.14912556 | E22: =C22/$C$6 -> -0.031750281 | F22: =B22-C22 -> -135084 | G22: =IFERROR(F22/ABS(C22),"n/a") -> -2.2244105
A24: ANÁLISIS VERTICAL (% sobre ventas) — Años 2023 y 2022
A25: Coste de ventas = 88,7% s/ventas (2023) vs 73,9% (2022): estructura de costes claramente variable, pero con fuerte deterioro de la eficiencia. El Margen Bruto cae al 11,3% (26,1% en 2022), lo que refleja que Acerinox no puede trasladar al precio la caída de la demanda ni los costes de materia prima.
A26: VAB = -4,9% s/ventas (+4,7% en 2022): los Otros gastos de explotación (principalmente servicios exteriores) absorben -18,7% de las ventas, convirtiendo al VAB en negativo. La empresa destruye valor añadido en 2023. Gastos de personal pesan 9,5% s/ventas (vs 6,8%) por el efecto denominador — no hay ajuste de plantilla proporcional a la caída de ventas.
A27: EBITDA = -14,4% s/ventas (-2,1% en 2022): pérdida operativa recurrente antes de amortizaciones. Con amortizaciones del 2,7% s/ventas, el BAII se sitúa en -17,1% (vs -3,7%). Los Gastos financieros suben al 3,0% s/ventas (0,8% en 2022). El Rdo. Neto final es -14,9% s/ventas (-3,2% en 2022). Política fiscal: el crédito fiscal positivo (impto +5,1% s/ventas) amortigua parcialmente las pérdidas.
A29: ANÁLISIS HORIZONTAL (variación 2023 vs 2022)
A30: Ventas: -31,3% (1.912.676 → 1.313.068 miles €). Señal de contracción severa del mercado del acero inoxidable o pérdida de cuota. El Coste de ventas cae solo un 17,7%, mucho menos que las ventas, por lo que el Margen Bruto se desploma un 70,2%. No hay flexibilidad en la estructura de costes variables para absorber la caída.
A31: VAB: pasa de +89.823 a -63.842 miles € (cae más del 170%). EBITDA empeora un 371% (de -39.994 a -188.562). BAII cae un 220% (de -70.259 a -224.976). Esta cascada evidencia un APALANCAMIENTO OPERATIVO FUERTEMENTE NEGATIVO: al operar con muchos costes fijos (Personal, Amortiz., Otros gtos.), una caída del 31% en ventas triplica la pérdida operativa.
A32: Gastos financieros: +141% (16.235 → 39.155 miles €), sumando más deterioro al Resultado. El Rdo. del ejercicio empeora un 222% (-60.728 → -195.812). El impuesto positivo (+66.658) indica activación de créditos fiscales por bases imponibles negativas, sólo recuperables si la empresa vuelve a beneficios futuros.
A34: PUNTO DE EQUILIBRIO (UMBRAL DE RENTABILIDAD)
A35: CONCEPTO | B35: 2023 (miles €) | C35: 2022 (miles €) | D35: Fórmula / Comentario
A36: Costes fijos (Personal + Amortiz. + Deterioro) | B36: =-B12-B14-B15 -> 161134 | C36: =-C12-C14-C15 -> 160082 | D36: Personal + Amortiz. + Deterioro (en valor absoluto)
A37: Costes variables (Coste de ventas + Otros gtos. expl. - Otros ingr.) | B37: =-B7-B9-B10 -> 1376910 | C37: =-C7-C9-C10 -> 1822853 | D37: Absorbidos proporcionalmente a las ventas
A38: Margen sobre ventas (1 - CV/V) | B38: =1-B37/B6 -> -0.048620483 | C38: =1-C37/C6 -> 0.046961953 | D38: % de cada euro vendido que queda tras costes variables
A39: PUNTO DE EQUILIBRIO (BAII = 0) | B39: =IF(B38<=0,"n/a (margen negativo: no existe PE)",B36/B38) -> n/a (margen negativo: no existe PE) | C39: =IF(C38<=0,"n/a (margen negativo: no existe PE)",C36/C38) -> 3408759.4 | D39: Costes fijos / Margen sobre ventas
A40: Cobertura del punto de equilibrio | B40: =IF(ISNUMBER(B39),B6/B39,"n/a") -> n/a | C40: =IF(ISNUMBER(C39),C6/C39,"n/a") -> 0.56110618 | D40: Ventas / Punto de equilibrio; >1 significa cubrir el PE
A42: Interpretación — Punto de equilibrio
A43: 2022: margen variable del 4,70% y costes fijos de 160.082 miles € ⇒ PE = 3.408.759 miles €. Con ventas de 1.912.676, la cobertura fue del 56% — ya entonces la empresa NO cubría el punto de equilibrio. 2023: margen variable NEGATIVO (-4,86%) ⇒ el punto de equilibrio MATEMÁTICAMENTE NO EXISTE (la fórmula arroja un valor absurdo) porque cada euro vendido genera pérdida adicional antes incluso de los costes fijos. Es el escenario más crítico: vender más empeora el resultado en vez de mejorarlo.
A44: Diagnóstico: Acerinox no tiene un problema de volumen sino de margen variable. Vender más en 2023 significaría perder más. La prioridad absoluta es RECUPERAR EL MARGEN BRUTO (subir precios, mejorar mix de producto hacia aleaciones de mayor valor añadido, reducir costes variables de materia prima). Solo cuando el margen variable vuelva a ser positivo tendrá sentido hablar de punto de equilibrio como referencia operativa.
A48: 6.2. ANÁLISIS DE LA RENTABILIDAD ECONÓMICA Y FINANCIERA Y SU DESCOMPOSICIÓN
A50: DATOS DE PARTIDA | B50: 2023 | C50: 2022
A51: Ventas (INCN) | B51: =B6 -> 1313068 | C51: =C6 -> 1912676
A52: BAII | B52: =B16 -> -224976 | C52: =C16 -> -70259
A53: BAI | B53: =B20 -> -262470 | C53: =C20 -> -83216
A54: Resultado del ejercicio (Bº Neto) | B54: =B22 -> -195812 | C54: =C22 -> -60728
A55: Activo total | B55: ='BALANCE DE SITUACIÓN'!C79 -> 1142438 | C55: ='BALANCE DE SITUACIÓN'!D79 -> 1193913
A56: Patrimonio Neto (Fondos Propios) | B56: ='BALANCE DE SITUACIÓN'!C84 -> 53265 | C56: ='BALANCE DE SITUACIÓN'!D84 -> 242867
A57: Pasivo total (No corriente + Corriente) | B57: =B55-B56 -> 1089173 | C57: =C55-C56 -> 951046
A58: Gastos financieros | B58: =-B18 -> 39155 | C58: =-C18 -> 16235
A60: A) RENTABILIDAD ECONÓMICA (ROA / Rendimiento)
A61: Fórmula: ROA = BAII / Activo total
A62: CONCEPTO | B62: 2023 | C62: 2022 | D62: Fórmula
A63: Rotación del activo (Ventas / Activo) | B63: =B51/B55 -> 1.149356 | C63: =C51/C55 -> 1.6020229 | D63: Ventas / Activo total
A64: Margen de ventas (BAII / Ventas) | B64: =B52/B51 -> -0.17133614 | C64: =C52/C51 -> -0.036733352 | D64: BAII / Ventas
A65: RENTABILIDAD ECONÓMICA (ROA) | B65: =B63*B64 -> -0.19692622 | C65: =C63*C64 -> -0.058847671 | D65: Rotación × Margen = BAII / Activo
A66: Comprobación directa (BAII / Activo) | B66: =B52/B55 -> -0.19692622 | C66: =C52/C55 -> -0.058847671
A68: B) RENTABILIDAD FINANCIERA (ROE) — Descomposición Método de Parés
A69: Fórmula: ROE = (Ventas/Activo) × (BAII/Ventas) × (Activo/FFPP) × (BAI/BAII) × (Rdo/BAI) = Rotación × Margen × Apalancamiento Fin. × Efecto Fiscal
A70: CONCEPTO | B70: 2023 | C70: 2022 | D70: Fórmula
A71: Rotación del activo | B71: =B51/B55 -> 1.149356 | C71: =C51/C55 -> 1.6020229 | D71: Ventas / Activo
A72: Margen de ventas | B72: =B52/B51 -> -0.17133614 | C72: =C52/C51 -> -0.036733352 | D72: BAII / Ventas
A73: Apalancamiento (Activo/FFPP) | B73: =B55/B56 -> 21.448193 | C73: =C55/C56 -> 4.9159128 | D73: Activo / FFPP
A74: Ratio coste financiero (BAI/BAII) | B74: =B53/B52 -> 1.1666578 | C74: =C53/C52 -> 1.1844177 | D74: BAI / BAII
A75: APALANCAMIENTO FINANCIERO TOTAL | B75: =B73*B74 -> 25.022701 | C75: =C73*C74 -> 5.8224939 | D75: (Activo/FFPP) × (BAI/BAII)
A76: Efecto fiscal | B76: =B54/B53 -> 0.74603574 | C76: =C54/C53 -> 0.72976351 | D76: Rdo / BAI
A77: RENTABILIDAD FINANCIERA (ROE) | B77: =B71*B72*B73*B74*B76 -> -3.6761851 | C77: =C71*C72*C73*C74*C76 -> -0.25004632 | D77: Rot × Marg × Apal × BAI/BAII × Ef.Fiscal
A78: Comprobación directa (Rdo / FFPP) | B78: =B54/B56 -> -3.6761851 | C78: =C54/C56 -> -0.25004632
A80: C) DIAGNÓSTICO DEL APALANCAMIENTO FINANCIERO
A81: CONCEPTO | B81: 2023 | C81: 2022 | D81: Referencia / Criterio
A82: Rendimiento del activo (ROA) | B82: =B65 -> -0.19692622 | C82: =C65 -> -0.058847671 | D82: Debe ser > Coste deuda
A83: Coste medio de la deuda (Gastos Fin / Pasivo) | B83: =B58/B57 -> 0.035949294 | C83: =C58/C57 -> 0.017070678 | D83: Gastos Fin / Pasivo total
A84: Diferencia ROA – Coste deuda | B84: =B82-B83 -> -0.23287552 | C84: =C82-C83 -> -0.075918349 | D84: Positiva ⇒ apalancamiento favorable
A85: Ratio de apalancamiento financiero (AF) | B85: =B75 -> 25.022701 | C85: =C75 -> 5.8224939 | D85: AF > 1 ⇒ la deuda es favorable para ROE
A87: ANÁLISIS 6.2 — Rentabilidad y apalancamiento
A88: Rentabilidad económica (ROA): Se deteriora de -5,88% (2022) a -19,69% (2023). La descomposición muestra que el problema es el MARGEN, que se desploma del -3,67% al -17,13%. La rotación también empeora (1,60 → 1,15) porque las ventas caen más que el activo. Al ser el ROA negativo en ambos ejercicios, el activo destruye valor: la empresa no genera beneficio operativo suficiente para cubrir el coste de su financiación.
A89: Rentabilidad financiera (ROE): Pasa de -25,0% en 2022 a un alarmante -367,6% en 2023. El empeoramiento se explica por: (1) margen y rotación negativos, y sobre todo (2) por el desplome del Patrimonio Neto (de 242.867 a 53.265 miles €) a causa de las pérdidas acumuladas, que dispara el ratio Activo/FFPP de 4,92 a 21,45. La empresa está muy cerca de la descapitalización.
A90: Apalancamiento financiero: Aunque el ratio AF calculado resulte >1 en ambos ejercicios (5,82 y 25,02), este resultado es ENGAÑOSO porque surge de dividir números negativos (BAI/BAII). Aplicando el criterio alternativo del Tema 5, comparamos ROA con Coste de la deuda: ROA 2023 = -19,7% vs CD = 3,6% ⇒ diferencial de -23,3 p.p. La deuda NO es favorable; el apalancamiento amplifica las pérdidas del accionista en lugar de mejorar su rentabilidad.
A91: Efecto fiscal: En torno a 0,73-0,75 en ambos años. Al ser BAI y Rdo. ambos negativos, este ratio positivo refleja que el crédito fiscal (impuesto positivo por activación de bases imponibles negativas) atenuúa las pérdidas del ejercicio en aproximadamente un 25-27%. Si la empresa no recupera la rentabilidad, la recuperabilidad de los activos por impuesto diferido podría cuestionarse.
A93: D) DESCOMPOSICIÓN DEL APALANCAMIENTO FINANCIERO (componentes por separado)
A94: CONCEPTO | B94: 2023 | C94: 2022 | D94: Interpretación
A95: Activo / Patrimonio Neto (A/PN) | B95: =B73 -> 21.448193 | C95: =C73 -> 4.9159128 | D95: Mide el peso de la deuda sobre los FFPP. Aumenta fuertemente (descapitalización).
A96: BAI / BAII | B96: =B74 -> 1.1666578 | C96: =C74 -> 1.1844177 | D96: Efecto de los gastos financieros sobre el BAII. Ratio engañoso con BAI y BAII negativos.
A97: APALANCAMIENTO FINANCIERO (A/PN × BAI/BAII) | B97: =B95*B96 -> 25.022701 | C97: =C95*C96 -> 5.8224939 | D97: AF > 1 matemáticamente pero el signo es espurio por beneficios negativos.
A99: E) TERMÓMETRO DE LA RENTABILIDAD — Comparativa con alternativas de inversión
A100: ALTERNATIVA DE INVERSIÓN | B100: Rentabilidad anual aprox. 2023 | C100: Nivel de riesgo | D100: Comparación con ROE Acerinox (-367,6%)
A101: Depósito bancario a plazo fijo | B101: 0.03 | C101: Muy bajo | D101: Muy superior a Acerinox
A102: Bono del Estado español 10 años | B102: 0.035 | C102: Bajo | D102: Muy superior a Acerinox
A103: Inflación media zona euro 2023 | B103: 0.054 | C103: — (referencia) | D103: Acerinox no preserva poder adquisitivo
A104: IBEX-35 (rendimiento medio anualizado) | B104: 0.08 | C104: Medio-alto | D104: Muy superior a Acerinox
A105: Fondo de renta variable global | B105: 0.1 | C105: Alto | D105: Muy superior a Acerinox
A106: ROE Acerinox 2023 | B106: =B77 -> -3.6761851 | C106: Muy alto (descapitalización) | D106: Destruye valor para el accionista
A108: F) RECOMENDACIÓN — ¿Conviene aumentar la deuda?
A109: CRITERIO | B109: Valor 2023 | C109: Condición favorable | D109: Veredicto
A110: ROA > Coste de la deuda | B110: ROA -19,7% vs CD 3,6% | C110: ROA debe superar CD | D110: INCUMPLE (diferencial -23,3 p.p.)
A111: Ratio de apalancamiento financiero (AF) | B111: AF aparente > 1 | C111: AF > 1 | D111: Se cumple solo numéricamente; el signo es espurio (beneficios negativos)
A112: Nivel de endeudamiento actual | B112: =B57/B55 -> 0.95337603 | C112: < 0,60 (prudente) | D112: MUY ALTO — cerca del 95% del activo es deuda
A113: VEREDICTO FINAL | B113: NO ENDEUDARSE | C113: — | D113: Prioridad: recuperar rentabilidad y RECAPITALIZAR (ampliación capital)
A115: Conclusión: A diferencia de Canoliva (ROA 10% > CD 1% y AF > 1, donde convendría endeudarse pero no por exceso de deuda actual), Acerinox está en la situación opuesta: el ROA es negativo y muy inferior al coste de la deuda, por lo que cualquier deuda adicional AMPLIFICA las pérdidas para el accionista. La prioridad estratégica es: (1) recuperar el margen bruto, (2) ampliación de capital para reforzar FFPP (cayeron un 78%) y evitar la descapitalización, (3) reducir deuda si es posible y renegociar condiciones. Solo cuando el ROA vuelva a ser claramente superior al coste de la deuda podría plantearse usar apalancamiento para mejorar ROE.

Sheet ANÁLISIS DEL FM
A1: 7. ANÁLISIS DEL FONDO DE MANIOBRA
A4: A) FONDO DE MANIOBRA: GLOBAL, OPERATIVO Y EXTRAOPERATIVO
A6: Concepto | B6: 2023 (miles €) | C6: 2022 (miles €) | D6: Variación abs. | E6: Variación %
A7: Activo Corriente (AC) | B7: ='BALANCE DE SITUACIÓN'!C36 -> 625068 | C7: ='BALANCE DE SITUACIÓN'!D36 -> 738462 | D7: =B7-C7 -> -113394 | E7: =IFERROR(D7/ABS(C7),"n/a") -> -0.15355428
A8: Pasivo Corriente (PC) | B8: ='BALANCE DE SITUACIÓN'!C127 -> 1031409 | C8: ='BALANCE DE SITUACIÓN'!D127 -> 893250 | D8: =B8-C8 -> 138159 | E8: =IFERROR(D8/ABS(C8),"n/a") -> 0.15467003
A9: FM GLOBAL (AC – PC) | B9: =B7-B8 -> -406341 | C9: =C7-C8 -> -154788 | D9: =B9-C9 -> -251553 | E9: =IFERROR(D9/ABS(C9),"n/a") -> -1.6251454
A11: FM OPERATIVO
A12: (+) Existencias | B12: ='BALANCE DE SITUACIÓN'!C38 -> 421245 | C12: ='BALANCE DE SITUACIÓN'!D38 -> 477896 | D12: =B12-C12 -> -56651 | E12: =IFERROR(D12/ABS(C12),"n/a") -> -0.11854253
A13: (+) Deudores comerciales y otras cuentas a cobrar | B13: ='BALANCE DE SITUACIÓN'!C51 -> 197821 | C13: ='BALANCE DE SITUACIÓN'!D51 -> 257849 | D13: =B13-C13 -> -60028 | E13: =IFERROR(D13/ABS(C13),"n/a") -> -0.23280292
A14: (+) Periodificaciones a corto plazo | B14: ='BALANCE DE SITUACIÓN'!C75 -> 1703 | C14: ='BALANCE DE SITUACIÓN'!D75 -> 1134 | D14: =B14-C14 -> 569 | E14: =IFERROR(D14/ABS(C14),"n/a") -> 0.50176367
A15: (=) AC operativo | B15: =SUM(B12:B14) -> 620769 | C15: =SUM(C12:C14) -> 736879 | D15: =B15-C15 -> -116110 | E15: =IFERROR(D15/ABS(C15),"n/a") -> -0.15756997
A16: (–) Acreedores comerciales y otras cuentas a pagar | B16: ='BALANCE DE SITUACIÓN'!C139 -> 277399 | C16: ='BALANCE DE SITUACIÓN'!D139 -> 222323 | D16: =B16-C16 -> 55076 | E16: =IFERROR(D16/ABS(C16),"n/a") -> 0.24772965
A17: (=) PC operativo | B17: =B16 -> 277399 | C17: =C16 -> 222323 | D17: =B17-C17 -> 55076 | E17: =IFERROR(D17/ABS(C17),"n/a") -> 0.24772965
A18: FM OPERATIVO (AC op. – PC op.) | B18: =B15-B17 -> 343370 | C18: =C15-C17 -> 514556 | D18: =B18-C18 -> -171186 | E18: =IFERROR(D18/ABS(C18),"n/a") -> -0.33268682
A20: FM EXTRAOPERATIVO
A21: (+) Inversiones en empresas del grupo a corto plazo | B21: ='BALANCE DE SITUACIÓN'!C61 -> 770 | C21: ='BALANCE DE SITUACIÓN'!D61 -> 0 | D21: =B21-C21 -> 770 | E21: =IFERROR(D21/ABS(C21),"n/a") -> n/a
A22: (+) Inversiones financieras a corto plazo | B22: ='BALANCE DE SITUACIÓN'!C68 -> 80 | C22: ='BALANCE DE SITUACIÓN'!D68 -> 308 | D22: =B22-C22 -> -228 | E22: =IFERROR(D22/ABS(C22),"n/a") -> -0.74025974
A23: (+) Efectivo y equivalentes | B23: ='BALANCE DE SITUACIÓN'!C76 -> 3449 | C23: ='BALANCE DE SITUACIÓN'!D76 -> 1275 | D23: =B23-C23 -> 2174 | E23: =IFERROR(D23/ABS(C23),"n/a") -> 1.705098
A24: (=) AC extraoperativo | B24: =SUM(B21:B23) -> 4299 | C24: =SUM(C21:C23) -> 1583 | D24: =B24-C24 -> 2716 | E24: =IFERROR(D24/ABS(C24),"n/a") -> 1.7157296
A25: (–) Deudas a corto plazo (financieras) | B25: ='BALANCE DE SITUACIÓN'!C132 -> 221802 | C25: ='BALANCE DE SITUACIÓN'!D132 -> 218497 | D25: =B25-C25 -> 3305 | E25: =IFERROR(D25/ABS(C25),"n/a") -> 0.015126066
A26: (–) Deudas con empresas del grupo a corto plazo | B26: ='BALANCE DE SITUACIÓN'!C138 -> 532208 | C26: ='BALANCE DE SITUACIÓN'!D138 -> 452430 | D26: =B26-C26 -> 79778 | E26: =IFERROR(D26/ABS(C26),"n/a") -> 0.17633225
A27: (=) PC extraoperativo | B27: =B25+B26 -> 754010 | C27: =C25+C26 -> 670927 | D27: =B27-C27 -> 83083 | E27: =IFERROR(D27/ABS(C27),"n/a") -> 0.12383314
A28: FM EXTRAOPERATIVO (AC extraop. – PC extraop.) | B28: =B24-B27 -> -749711 | C28: =C24-C27 -> -669344 | D28: =B28-C28 -> -80367 | E28: =IFERROR(D28/ABS(C28),"n/a") -> -0.12006831
A29: COMPROBACIÓN: FM global = FM operativo + FM extraoperativo | B29: =B18+B28 -> -406341 | C29: =C18+C28 -> -154788
A31: B) CÁLCULO DE LOS PLAZOS MEDIOS (en días)
A33: Datos base (miles €) | B33: 2023 | C33: 2022
A34: Ventas (INCN) | B34: ='ANÁLISIS CUENTA PyG'!B6 -> 1313068 | C34: ='ANÁLISIS CUENTA PyG'!C6 -> 1912676
A35: Compras (Aprovisionamientos, valor abs.) | B35: =-'CUENTA DE PÉRDIDAS Y GANANCIAS'!C10 -> 1137455 | C35: =-'CUENTA DE PÉRDIDAS Y GANANCIAS'!D10 -> 1450909
A36: Variación de existencias (PT+PC) | B36: ='CUENTA DE PÉRDIDAS Y GANANCIAS'!C8 -> -33140 | C36: ='CUENTA DE PÉRDIDAS Y GANANCIAS'!D8 -> 11384
A37: Coste de fabricación (Compras ± Var. Exist. totales) | B37: =B35-B36 -> 1170595 | C37: =C35-C36 -> 1439525
A38: Coste de ventas (Aprovisionamientos ± Var. Exist., valor abs.) | B38: =-'ANÁLISIS CUENTA PyG'!B7 -> 1164466 | C38: =-'ANÁLISIS CUENTA PyG'!C7 -> 1414210
A39: Materias primas (saldo) | B39: ='BALANCE DE SITUACIÓN'!C40 -> 160765 | C39: ='BALANCE DE SITUACIÓN'!D40 -> 184275
A40: Productos en curso (saldo) | B40: ='BALANCE DE SITUACIÓN'!C43 -> 124468 | C40: ='BALANCE DE SITUACIÓN'!D43 -> 132594
A41: Productos terminados + Subproductos (saldo) | B41: ='BALANCE DE SITUACIÓN'!C46+'BALANCE DE SITUACIÓN'!C49 -> 136012 | C41: ='BALANCE DE SITUACIÓN'!D46+'BALANCE DE SITUACIÓN'!D49 -> 161027
A42: Clientes (ventas + grupo − anticipos) | B42: ='BALANCE DE SITUACIÓN'!C54+'BALANCE DE SITUACIÓN'!C55-'BALANCE DE SITUACIÓN'!C148 -> 172824 | C42: ='BALANCE DE SITUACIÓN'!D54+'BALANCE DE SITUACIÓN'!D55-'BALANCE DE SITUACIÓN'!D148 -> 251468
A43: Proveedores (acreedores comerciales y otras cuentas a pagar) | B43: ='BALANCE DE SITUACIÓN'!C139 -> 277399 | C43: ='BALANCE DE SITUACIÓN'!D139 -> 222323
A45: Ratio de plazo | B45: 2023 (días) | C45: 2022 (días) | D45: Variación | E45: Fórmula
A46: Plazo almacenamiento Materias Primas | B46: =B39/B35*365 -> 51.588173 | C46: =C39/C35*365 -> 46.357404 | D46: =B46-C46 -> 5.2307685 | E46: MP / Compras × 365
A47: Plazo Productos en Curso | B47: =B40/B37*365 -> 38.810024 | C47: =C40/C37*365 -> 33.619986 | D47: =B47-C47 -> 5.1900382 | E47: PC / Coste fabricación × 365
A48: Plazo Productos Terminados | B48: =B41/B38*365 -> 42.632743 | C48: =C41/C38*365 -> 41.560203 | D48: =B48-C48 -> 1.07254 | E48: PT / Coste ventas × 365
A49: Plazo de Cobro a Clientes | B49: =B42/B34*365 -> 48.040741 | C49: =C42/C34*365 -> 47.988169 | D49: =B49-C49 -> 0.052571771 | E49: Clientes / Ventas × 365
A50: CICLO DE MADURACIÓN (días) | B50: =B46+B47+B48+B49 -> 181.07168 | C50: =C46+C47+C48+C49 -> 169.52576 | D50: =B50-C50 -> 11.545918 | E50: Suma plazos MP+PC+PT+Cobro
A51: Plazo de Pago a Proveedores | B51: =B43/B35*365 -> 89.015069 | C51: =C43/C35*365 -> 55.929004 | D51: =B51-C51 -> 33.086065 | E51: Proveedores / Compras × 365
A52: CICLO DE CAJA (días) | B52: =B50-B51 -> 92.056612 | C52: =C50-C51 -> 113.59676 | D52: =B52-C52 -> -21.540146 | E52: Ciclo Maduración – Plazo Pago
A54: C) ANÁLISIS VERTICAL (2023)
A55: Fondo de Maniobra — El FM global es NEGATIVO (-406.341 miles €), lo que revela que Acerinox financia parte de su Activo No Corriente con Pasivo Corriente. Situación de desequilibrio financiero con riesgo de suspensión de pagos. El FM operativo es positivo (343.370) porque las partidas de explotación (existencias y clientes) superan a los acreedores comerciales. Sin embargo, el FM extraoperativo es muy negativo (-749.711) por la fortísima carga de deudas financieras a corto plazo (221.802) y, sobre todo, deudas con empresas del grupo (532.208), que superan en mucho a la tesorería e inversiones financieras disponibles (4.299).
A56: Plazos (2023) — Empresa industrial: stock de MP 51,6 días, PC 38,8 días y PT 42,6 días, sumando 133 días de almacenamiento. Plazo de cobro 48,0 días. Ciclo de maduración 181 días (por encima de la media de un industrial típico, 90-120 días). Plazo de pago a proveedores 89,0 días, por encima del límite legal de 60 días (Ley 15/2010). Ciclo de caja 92 días: la empresa debe financiar con recursos propios o ajenos 92 días de actividad.
A58: D) ANÁLISIS HORIZONTAL (2023 vs 2022)
A59: Fondo de Maniobra — El FM global empeora un 162% (de -154.788 a -406.341), pasando de un desequilibrio leve a uno crítico. El FM operativo cae un 33% (de 514.556 a 343.370), principalmente por el aumento de proveedores (+25%) y la reducción de clientes (-23%) y existencias (-12%) ligada a la caída de ventas (-31%). El FM extraoperativo empeora un 12% (más negativo) porque crecen las deudas con el grupo (+18%) mientras la tesorería apenas ha subido.
A60: Plazos — El ciclo de maduración se alarga 10 días (181 vs 171). Todos los plazos de almacenamiento suben: MP +5 días, PC +5 días, PT +1 día; efecto típico cuando caen las ventas sin ajustar compras. El plazo de cobro se mantiene prácticamente plano (48 vs 48). En cambio, el plazo de PAGO a proveedores se dispara 33 días (89 vs 56): la empresa retrasa el pago para compensar el empeoramiento de liquidez. Gracias a ello, el ciclo de caja se reduce respecto a 2022, pero esta mejora es engañosa: no viene de mayor eficiencia operativa sino de financiarse a costa de los proveedores.
A62: E) CONCLUSIONES
A63: 1. DESEQUILIBRIO FINANCIERO GRAVE: FM global negativo y deteriorado. La empresa financia inversiones estructurales con deuda a corto plazo, principalmente préstamos intragrupo.
A64: 2. PLAZOS POCO EFICIENTES: Ciclo de maduración de 181 días es elevado. Existencias crecen a pesar de la caída de ventas.
A65: 3. DEPENDENCIA DEL GRUPO Y PROVEEDORES: La principal fuente de financiación corriente son las deudas con empresas del grupo (532 Mm€, +18%) y los acreedores comerciales (277 Mm€, +25%). Alargar el pago más allá de los 60 días legales (Ley 15/2010) es un riesgo de morosidad y de relación con los proveedores.
A66: 4. RECOMENDACIÓN: Renegociar deuda intragrupo a largo plazo (conversión en Pasivo No Corriente o en capital); acortar ciclo de maduración reduciendo stocks y plazo de cobro; evitar aumentar más el plazo de pago a proveedores para no incurrir en morosidad.

Sheet EFE
A1: 8. ANÁLISIS DEL ESTADO DE FLUJOS DE EFECTIVO (EFE) — ACERINOX EUROPA S.A.U.
A3: A) Estado oficial — formato PGC (miles €)
A5: Concepto | B5: 2023 | C5: 2022 | D5: Variación
A6: A) FLUJOS DE EFECTIVO DE ACTIVIDADES DE EXPLOTACIÓN | B6: =B7+B8+B19+B25 -> -46571 | C6: =C7+C8+C19+C25 -> -80827 | D6: =B6-C6 -> 34256
A7: 1. Resultado del ejercicio antes de impuestos | B7: -262470 | C7: -83216 | D7: =B7-C7 -> -179254
A8: 2. Ajustes del resultado | B8: =SUM(B9:B18) -> 53052 | C8: =SUM(C9:C18) -> 78303 | D8: =B8-C8 -> -25251
A9: a) Amortización del inmovilizado (+) | B9: 36003 | C9: 30024 | D9: =B9-C9 -> 5979
A10: b) Correcciones valorativas por deterioro (+/-) | B10: -21319 | C10: 33304 | D10: =B10-C10 -> -54623
A11: c) Variación de provisiones (+/-) | B11: 7166 | C11: 6375 | D11: =B11-C11 -> 791
A12: d) Imputación de subvenciones (-) | B12: -8489 | C12: -6409 | D12: =B12-C12 -> -2080
A13: e) Resultados por bajas y enajenaciones (+/-) | B13: 411 | C13: 242 | D13: =B13-C13 -> 169
A14: g) Ingresos financieros (-) | B14: -350 | C14: -1903 | D14: =B14-C14 -> 1553
A15: h) Gastos financieros (+) | B15: 39155 | C15: 16235 | D15: =B15-C15 -> 22920
A16: k) Otros ingresos y gastos (+/-) | B16: 475 | C16: 435 | D16: =B16-C16 -> 40
A19: 3. Cambios en el capital corriente | B19: =SUM(B20:B24) -> 200444 | C19: =SUM(C20:C24) -> -61912 | D19: =B19-C19 -> 262356
A20: a) Existencias (+/-) | B20: 86779 | C20: -81815 | D20: =B20-C20 -> 168594
A21: b) Deudores y otras cuentas a cobrar (+/-) | B21: 60028 | C21: 188460 | D21: =B21-C21 -> -128432
A22: c) Otros activos corrientes (+/-) | B22: -341 | C22: 3490 | D22: =B22-C22 -> -3831
A23: d) Acreedores y otras cuentas a pagar (+/-) | B23: 55759 | C23: -172748 | D23: =B23-C23 -> 228507
A24: e) Otros pasivos corrientes (+/-) | B24: -1781 | C24: 701 | D24: =B24-C24 -> -2482
A25: 4. Otros flujos de efectivo de explotación | B25: =SUM(B26:B28) -> -37597 | C25: =SUM(C26:C28) -> -14002 | D25: =B25-C25 -> -23595
A26: a) Pagos de intereses (-) | B26: -37683 | C26: -15905 | D26: =B26-C26 -> -21778
A27: c) Cobros de intereses (+) | B27: 0 | C27: 1903 | D27: =B27-C27 -> -1903
A28: d) Pagos (cobros) por impuesto sobre beneficios | B28: 86 | C28: 0 | D28: =B28-C28 -> 86
A30: B) FLUJOS DE EFECTIVO DE INVERSIÓN | B30: =B31+B35 -> -43498 | C30: =C31+C35 -> -44996 | D30: =B30-C30 -> 1498
A31: 6. Pagos por inversiones (-) | B31: =SUM(B32:B34) -> -43498 | C31: =SUM(C32:C34) -> -45009 | D31: =B31-C31 -> 1511
A32: b) Inmovilizado intangible | B32: -575 | C32: -259 | D32: =B32-C32 -> -316
A33: c) Inmovilizado material | B33: -42921 | C33: -44425 | D33: =B33-C33 -> 1504
A34: e) Otros activos financieros | B34: -2 | C34: -325 | D34: =B34-C34 -> 323
A35: 7. Cobros por desinversiones (+) | B35: 0 | C35: 13 | D35: =B35-C35 -> -13
A36: 9. Cobros y pagos por instrumentos de patrimonio | B36: 0 | C36: -3 | D36: =B36-C36 -> 3
A37: 10. Cobros y pagos por instrumentos de pasivo financiero | B37: =SUM(B38:B41) -> 91635 | C37: =SUM(C38:C41) -> 125826 | D37: =B37-C37 -> -34191
A38: a) Emisión: Deudas con entidades de crédito | B38: 4389 | C38: 76066 | D38: =B38-C38 -> -71677
A39: b) Emisión: Deudas con empresas del grupo | B39: 84082 | C39: 48902 | D39: =B39-C39 -> 35180
A40: c) Emisión: Otras deudas | B40: 3164 | C40: 870 | D40: =B40-C40 -> 2294
A41: d) Devolución y amortización de deudas | B41: 0 | C41: -12 | D41: =B41-C41 -> 12
A44: C) FLUJOS DE EFECTIVO DE FINANCIACIÓN | B44: =B36+B37 -> 91635 | C44: =C36+C37 -> 125823 | D44: =B44-C44 -> -34188
A45: E) AUMENTO/DISMINUCIÓN NETA DEL EFECTIVO (A+B+C) | B45: =B6+B30+B44 -> 1566 | C45: =C6+C30+C44 -> 0 | D45: =B45-C45 -> 1566
A46: Efectivo y equivalentes al inicio del ejercicio | B46: 1275 | C46: 1275 | D46: =B46-C46 -> 0
A47: Efectivo y equivalentes al final del ejercicio (segun EFE) | B47: =B45+B46 -> 2841 | C47: =C45+C46 -> 1275 | D47: =B47-C47 -> 1566
A48: Nota técnica: El efectivo al cierre del ejercicio 2023 según el EFE oficial (2.841 miles €) difiere del saldo de la rúbrica VII 'Efectivo y otros activos líquidos equivalentes' del Activo Corriente del Balance (3.449 miles €) en 608 miles €. Esta discrepancia, habitual cuando se incluyen descubiertos bancarios netos o equivalentes asimilados, no afecta a la consistencia interna del EFE: la identidad A+B+C=ΔEfectivo se cumple en ambos ejercicios (+1.566 en 2023, 0 en 2022). Para el análisis se utilizan los datos del EFE oficial.
A49: B) Reclasificación analítica gerencial — enfoque por generación de caja (miles €)
A51: Magnitud | B51: 2023 | C51: 2022 | D51: Var.
A52: EBITDA (BAII + Amortizaciones + Resultados por bajas) | B52: ='CUENTA DE PÉRDIDAS Y GANANCIAS'!C37+B9+B13 -> -188562 | C52: ='CUENTA DE PÉRDIDAS Y GANANCIAS'!D37+C9+C13 -> -39993 | D52: =B52-C52 -> -148569
A53: (+/-) Variación del capital corriente operativo | B53: =B19 -> 200444 | C53: =C19 -> -61912 | D53: =B53-C53 -> 262356
A54: (-) Impuestos pagados | B54: =B28 -> 86 | C54: =C28 -> 0 | D54: =B54-C54 -> 86
A55: (-) Intereses pagados netos | B55: =B26+B27 -> -37683 | C55: =C26+C27 -> -14002 | D55: =B55-C55 -> -23681
A56: Flujo de Caja Operativo (FCO) = subtotal A oficial | B56: =B6 -> -46571 | C56: =C6 -> -80827 | D56: =B56-C56 -> 34256
A57: (-) CAPEX (inversión neta en inmovilizado) = subtotal B | B57: =B30 -> -43498 | C57: =C30 -> -44996 | D57: =B57-C57 -> 1498
A58: Flujo de Caja Libre (FCF) = FCO + CAPEX | B58: =B56+B57 -> -90069 | C58: =C56+C57 -> -125823 | D58: =B58-C58 -> 35754
A59: (+) Flujos de financiación (subtotal C) | B59: =B44 -> 91635 | C59: =C44 -> 125823 | D59: =B59-C59 -> -34188
A60: = Variación neta de tesorería (cuadra con Δ Balance D76-C76) | B60: =B58+B59 -> 1566 | C60: =C58+C59 -> 0 | D60: =B60-C60 -> 1566
A64: C) Diagnóstico de la generación y aplicación de caja
A66: Conclusión 1 — EBITDA y FCO: deterioro brusco de la generación operativa
A67: El EBITDA cae de -39.994 mil € (2022) a -188.562 mil € (2023): la actividad ordinaria deja de cubrir incluso amortizaciones. El FCO oficial es muy negativo en ambos ejercicios (-46.571 mil € en 2023, -80.827 mil € en 2022), pero mejora 34.256 mil € gracias a una fuerte liberación de capital corriente (+200.444 mil €) por reducción de existencias (+86.779) y cobros de clientes (+60.028). Esta mejora es NO recurrente: el dato estructural sigue siendo de crisis operativa.
A69: Conclusión 2 — CAPEX sostenido pese a la crisis operativa
A70: La empresa mantiene un CAPEX elevado: -43.498 mil € en 2023 y -44.996 mil € en 2022 (esencialmente inmovilizado material). En un ejercicio con FCO negativo de -46.571 mil €, el CAPEX deja un FCF de -90.069 mil €, que debe financiarse íntegramente con deuda. La intensidad inversora compromete aún más la solvencia futura.
A72: Conclusión 3 — La financiación absorbe todo el déficit de caja (“dependencia del grupo”)
A73: El flujo neto de financiación es muy positivo: +91.635 mil € en 2023 y +125.823 mil € en 2022, procedente del desglose oficial de la memoria. Este flujo corresponde principalmente al aumento de deudas con empresas del grupo (+84.082 en 2023) y, en menor medida, con entidades de crédito (+4.389). La matriz está capitalizando a la filial vía deuda, lo cual evita una crisis de liquidez pero traslada la dependencia al apoyo de Acerinox S.A.
A75: Conclusión 4 — Pagos de intereses se duplican y compriman aún más la caja
A76: Los pagos por intereses pasan de -15.905 mil € (2022) a -37.683 mil € (2023), un +137%. Combinado con un EBITDA destruido, la empresa pierde capacidad de hacer frente a su servicio de la deuda con flujos propios. La cobertura EBITDA/Intereses es netamente negativa: el servicio de la deuda se paga con caja procedente del grupo.
A78: Conclusión 5 — Variación de tesorería cuadrada y reducida
A79: La variación neta de tesorería 2023 según el EFE oficial es de +1.566 mil €. El saldo de la rúbrica VII del Balance al cierre (3.449 €) presenta una discrepancia de 608 € con el efectivo final del EFE, habitual por reclasificaciones de equivalentes. El nivel absoluto de tesorería sigue siendo muy reducido (~0,25% del activo total), lo que confirma una posición de liquidez frágil aunque sin tensiones inmediatas gracias al respaldo del grupo.
A82: D) Ratios de calidad de los flujos de caja
A84: Ratio | B84: 2023 | C84: 2022 | D84: Interpretación
A85: FCO / Ventas | B85: =B56/'CUENTA DE PÉRDIDAS Y GANANCIAS'!C4 -> -0.035467318 | C85: =C56/'CUENTA DE PÉRDIDAS Y GANANCIAS'!D4 -> -0.042258595 | D85: Caja generada por cada € vendido. Negativo en ambos: la actividad destruye caja.
A86: EBITDA / Ventas (margen EBITDA) | B86: =B52/'CUENTA DE PÉRDIDAS Y GANANCIAS'!C4 -> -0.14360414 | C86: =C52/'CUENTA DE PÉRDIDAS Y GANANCIAS'!D4 -> -0.020909448 | D86: Rentabilidad operativa antes de amortizaciones. Negativo en 2023 (-15,5%) ⇒ destrucción de valor en la actividad ordinaria.
A87: FCF / FCO (intensidad inversora) | B87: =IFERROR(B58/B56,"n/a") -> 1.9340147 | C87: =IFERROR(C58/C56,"n/a") -> 1.5566952 | D87: Cuanto más elevado y negativo, mayor déficit de caja libre tras CAPEX.
A88: Cobertura intereses con FCO (FCO antes intereses / Intereses) | B88: =IFERROR((B56-B55)/ABS(B55),"n/a") -> -0.23586233 | C88: =IFERROR((C56-C55)/ABS(C55),"n/a") -> -4.7725325 | D88: Debe ser > 1. Negativo o bajo ⇒ el FCO no cubre el servicio de la deuda.
A89: Autofinanciación del CAPEX (FCO / |CAPEX|) | B89: =IFERROR(B56/ABS(B57),"n/a") -> -1.0706469 | C89: =IFERROR(C56/ABS(C57),"n/a") -> -1.7963152 | D89: % del CAPEX cubierto con caja operativa. < 100% ⇒ hay que financiar la diferencia con deuda.
A90: Dependencia de financiación externa (Flujos C / (|FCO|+|CAPEX|)) | B90: =IFERROR(B44/(ABS(B6)+ABS(B30)),"n/a") -> 1.0173867 | C90: =IFERROR(C44/(ABS(C6)+ABS(C30)),"n/a") -> 1 | D90: % en que la financiación externa cubre el déficit de caja libre. > 100% indica que la deuda no sólo cubre el FCF sino que además engorda la posición de tesorería.
A91: Saldo de tesorería / Activo total | B91: ='BALANCE DE SITUACIÓN'!C76/'BALANCE DE SITUACIÓN'!C79 -> 0.0030189822 | C91: ='BALANCE DE SITUACIÓN'!D76/'BALANCE DE SITUACIÓN'!D79 -> 0.001067917 | D91: Liquidez inmediata sobre el balance. Muy bajo ⇒ riesgo de liquidez si falla el apoyo del grupo.
A94: E) Conclusión integrada del análisis de flujos
A96: Síntesis de las cinco grandes lecturas del EFE 2023
A97: 1. La actividad ordinaria deja de generar caja: el EBITDA se hunde de -39.994 a -188.562 mil € (margen EBITDA -14,4%) y el FCO sigue siendo muy negativo (-46.571 mil €) pese a haber liberado 200 millones de capital corriente. Sin esa palanca puntual, el FCO real estructural sería del orden de -250 millones.
A98: 2. El CAPEX se mantiene en niveles de inversión normal (-43,5 millones, similar a 2022). En un contexto donde el FCO es negativo, todo este CAPEX se financia con deuda: el FCF llega a -90,1 millones, frente a -125,8 millones en 2022.
A99: 3. La financiación externa absorbe íntegramente el déficit: +87,9 millones en 2023 cubren el 97,6% del FCF negativo. Esta financiación procede mayoritariamente del grupo Acerinox (cuentas con empresas del grupo) y de pólizas a corto plazo con entidades de crédito. La filial es funcionalmente sostenida por la matriz.
A100: 4. El servicio de la deuda se ha encarecido: pagos por intereses x2,4 (de 15,9 a 37,7 millones) por la subida de tipos del BCE. La cobertura de intereses con FCO es negativa, signo claro de tensión financiera estructural.
A101: 5. La tesorería final (2.841 mil € según EFE; 3.449 € según Balance, ~0,25% del activo) es testimonial: la operativa diaria solo es posible porque existen líneas y cuentas con la matriz a disposición inmediata. La empresa, aislada de Acerinox S.A., tendría una crisis de liquidez inmediata.
A103: Veredicto
A104: El análisis de flujos confirma el diagnóstico de los estados anteriores: ACERINOX EUROPA S.A.U. atraviesa una crisis operativa profunda en 2023 (huelgas, demanda débil, costes energéticos) que destruye la capacidad de generación de caja propia. La situación no ha desembocado en concurso porque el grupo Acerinox proporciona financiación intra-grupo abundante y a coste reducido (coste medio 2,3%). La sostenibilidad a medio plazo depende de:
A105: • Recuperación del margen EBITDA (vuelta a tasas históricas +5/+8%)
A106: • Continuidad del apoyo financiero de la matriz
A107: • Contención del CAPEX hasta que la actividad se normalice
A108: • Gestión activa del coste de la deuda (refinanciación a tipos más bajos cuando el BCE relaje)
